[
  {
    "@context": "/contexts/Card",
    "@id": "/cards/ALT_DUSTEROP_P_AX_97_C",
    "@type": "Card",
    "cardType": {
      "@id": "/card_types/01GE7AC9X35JXEQZJBBD6E4BKX",
      "@type": "CardType",
      "reference": "SPELL",
      "id": "01GE7AC9X35JXEQZJBBD6E4BKX",
      "name": "Spell"
    },
    "cardSubTypes": [
      {
        "@type": "CardSubType",
        "@id": "/.well-known/genid/59caff56660e39a58516",
        "reference": "DISRUPTION",
        "id": "01HKAGPH80FC347E2P8841D298",
        "name": "Disruption"
      }
    ],
    "cardSet": {
      "@id": "/card_sets/DUSTEROP",
      "@type": "CardSet",
      "id": "01K4YGEBN10S3MMN6J9CW5B4AC",
      "reference": "DUSTEROP",
      "name": "Seeds of Unity - Organized Play"
    },
    "rarity": {
      "@type": "Rarity",
      "@id": "/.well-known/genid/ec4fdf60286a3ffccb83",
      "reference": "COMMON",
      "id": "01GE7AC9WEQKW1Y1BF8SCY745A",
      "name": "Common"
    },
    "imagePath": "https://altered-prod-eu.s3.amazonaws.com/Art/DUSTEROP/CARDS/ALT_DUSTEROP_P_AX_97/JPG/en_US/c3a8f6714aa1cd27a4eb43606ddf5f38.jpg",
    "assets": {
      "WEB": [
        "https://altered-prod-eu.s3.amazonaws.com/Art/DUSTEROP/CARDS/ALT_DUSTEROP_P_AX_97/WEB_795151e3f184bb5e6c978bcf3898680d",
        "https://altered-prod-eu.s3.amazonaws.com/Art/DUSTEROP/CARDS/ALT_DUSTEROP_P_AX_97/WEB_e42eb10738aa8551bc84f3728c009ca3"
      ]
    },
    "lowerPrice": 0,
    "qrUrlDetail": "https://qr.altered.gg/ALT_DUSTEROP_P_AX_97_C",
    "isOwnerless": false,
    "reference": "ALT_DUSTEROP_P_AX_97_C",
    "id": "01K4YGECGNA57ENJ74TZQMQ0GJ",
    "mainFaction": {
      "@id": "/factions/AX",
      "@type": "Faction",
      "reference": "AX",
      "color": "#8c432a",
      "id": "01GE7AC9XBG707G19F03A95TH1",
      "name": "Axiom"
    },
    "allImagePath": {
      "fr-fr": "https://altered-prod-eu.s3.amazonaws.com/Art/DUSTEROP/CARDS/ALT_DUSTEROP_P_AX_97/JPG/fr_FR/72b53ae3119a660c433d835a7e365308.jpg",
      "en-us": "https://altered-prod-eu.s3.amazonaws.com/Art/DUSTEROP/CARDS/ALT_DUSTEROP_P_AX_97/JPG/en_US/c3a8f6714aa1cd27a4eb43606ddf5f38.jpg",
      "it-it": "",
      "es-es": "",
      "de-de": ""
    },
    "name": "Failed Demo",
    "elements": {
      "MAIN_COST": "2",
      "RECALL_COST": "2",
      "MAIN_EFFECT": "[[Fleeting]].  Exhaust a card in your Reserve. If you do, send to Reserve target Character with Base Cost {3} or less."
    },
    "isSuspended": false,
    "isErrated": false,
    "isBanned": false,
    "isSerialized": false,
    "isParentSerialized": false,
    "collectorNumber": "SDUOP-001-C-EN"
  },
  {
    "@context": "/contexts/Card",
    "@id": "/cards/ALT_DUSTEROP_P_AX_93_R1",
    "@type": "Card",
    "cardType": {
      "@id": "/card_types/01H19NWA92A4ERAC4ATMSZNASS",
      "@type": "CardType",
      "reference": "CHARACTER",
      "id": "01H19NWA92A4ERAC4ATMSZNASS",
      "name": "Character"
    },
    "cardSubTypes": [
      {
        "@type": "CardSubType",
        "@id": "/.well-known/genid/5ea0f971f107287ee47d",
        "reference": "BUREAUCRAT",
        "id": "01HKAGVBV23NSWD6EXJXSKK3F8",
        "name": "Bureaucrat"
      }
    ],
    "cardSet": {
      "@id": "/card_sets/DUSTEROP",
      "@type": "CardSet",
      "id": "01K4YGEBN10S3MMN6J9CW5B4AC",
      "reference": "DUSTEROP",
      "name": "Seeds of Unity - Organized Play"
    },
    "rarity": {
      "@type": "Rarity",
      "@id": "/.well-known/genid/f7649067658bfa42c3ce",
      "reference": "RARE",
      "id": "01GE7AC9WY6PK56RADXXD6P1T5",
      "name": "Rare"
    },
    "imagePath": "https://altered-prod-eu.s3.amazonaws.com/Art/DUSTEROP/CARDS/ALT_DUSTEROP_P_AX_93/JPG/en_US/e2632158af9040e69276aba342eacfb2.jpg",
    "assets": {
      "WEB": [
        "https://altered-prod-eu.s3.amazonaws.com/Art/DUSTEROP/CARDS/ALT_DUSTEROP_P_AX_93/WEB_7720f60668295194acbe8529d4105be5",
        "https://altered-prod-eu.s3.amazonaws.com/Art/DUSTEROP/CARDS/ALT_DUSTEROP_P_AX_93/WEB_51f54f4926ee4e7fab0cda0a6672bc29",
        "https://altered-prod-eu.s3.amazonaws.com/Art/DUSTEROP/CARDS/ALT_DUSTEROP_P_AX_93/WEB_cb5969a59afad3be62b1ea54b1652d17"
      ]
    },
    "lowerPrice": 0,
    "qrUrlDetail": "https://qr.altered.gg/ALT_DUSTEROP_P_AX_93_R1",
    "isOwnerless": false,
    "reference": "ALT_DUSTEROP_P_AX_93_R1",
    "id": "01K4YGECGRVP002XYTEWX1RAJM",
    "mainFaction": {
      "@id": "/factions/AX",
      "@type": "Faction",
      "reference": "AX",
      "color": "#8c432a",
      "id": "01GE7AC9XBG707G19F03A95TH1",
      "name": "Axiom"
    },
    "allImagePath": {
      "fr-fr": "https://altered-prod-eu.s3.amazonaws.com/Art/DUSTEROP/CARDS/ALT_DUSTEROP_P_AX_93/JPG/fr_FR/811c41049500cfe78509f3893eabe51e.jpg",
      "en-us": "https://altered-prod-eu.s3.amazonaws.com/Art/DUSTEROP/CARDS/ALT_DUSTEROP_P_AX_93/JPG/en_US/e2632158af9040e69276aba342eacfb2.jpg",
      "it-it": "",
      "es-es": "",
      "de-de": ""
    },
    "name": "Reka Magnate",
    "elements": {
      "MAIN_COST": "3",
      "RECALL_COST": "3",
      "OCEAN_POWER": "3",
      "FOREST_POWER": "2",
      "MOUNTAIN_POWER": "2",
      "MAIN_EFFECT": "{R} Choose one, #or exhaust a Permanent you control to choose both:#  • [Sabotage].  • Create a [Manaseed] token in your Landmarks."
    },
    "isSuspended": false,
    "isErrated": false,
    "isBanned": false,
    "isSerialized": false,
    "isParentSerialized": false,
    "collectorNumber": "SDUOP-007-R-EN"
  },
  {
    "@context": "/contexts/Card",
    "@id": "/cards/ALT_DUSTEROP_A_AX_98_C",
    "@type": "Card",
    "cardType": {
      "@id": "/card_types/01GE7AC9X35JXEQZJBBD6E4BKX",
      "@type": "CardType",
      "reference": "SPELL",
      "id": "01GE7AC9X35JXEQZJBBD6E4BKX",
      "name": "Spell"
    },
    "cardSubTypes": [
      {
        "@type": "CardSubType",
        "@id": "/.well-known/genid/fbaa37dc232041bf5b41",
        "reference": "CONJURATION",
        "id": "01HKAGQJMGEVS21MCGWDGG8KW0",
        "name": "Conjuration"
      },
      {
        "@type": "CardSubType",
        "@id": "/.well-known/genid/7e0521fb327373ebf40c",
        "reference": "MANEUVER",
        "id": "01HKAGPGT0M24AWMMF30CN0NT4",
        "name": "Maneuver"
      }
    ],
    "cardSet": {
      "@id": "/card_sets/DUSTEROP",
      "@type": "CardSet",
      "id": "01K4YGEBN10S3MMN6J9CW5B4AC",
      "reference": "DUSTEROP",
      "name": "Seeds of Unity - Organized Play"
    },
    "rarity": {
      "@type": "Rarity",
      "@id": "/.well-known/genid/2affdf4020460d6b99fc",
      "reference": "COMMON",
      "id": "01GE7AC9WEQKW1Y1BF8SCY745A",
      "name": "Common"
    },
    "imagePath": "https://altered-prod-eu.s3.amazonaws.com/Art/DUSTEROP/CARDS/ALT_DUSTEROP_A_AX_98/JPG/en_US/29d4d0dd1b6f64ae9b43aa0047a7099a.jpg",
    "assets": {
      "WEB": [
        "https://altered-prod-eu.s3.amazonaws.com/Art/DUSTEROP/CARDS/ALT_DUSTEROP_A_AX_98/WEB_3bf03c8d4b745653df54077fc17339e7",
        "https://altered-prod-eu.s3.amazonaws.com/Art/DUSTEROP/CARDS/ALT_DUSTEROP_A_AX_98/WEB_31fa15d61fa8a2f1869d8fce838a0cdd"
      ]
    },
    "lowerPrice": 0,
    "qrUrlDetail": "https://qr.altered.gg/ALT_DUSTEROP_A_AX_98_C",
    "isOwnerless": false,
    "reference": "ALT_DUSTEROP_A_AX_98_C",
    "id": "01K4YGECGRVP002XYTEWX1RAJT",
    "mainFaction": {
      "@id": "/factions/AX",
      "@type": "Faction",
      "reference": "AX",
      "color": "#8c432a",
      "id": "01GE7AC9XBG707G19F03A95TH1",
      "name": "Axiom"
    },
    "allImagePath": {
      "fr-fr": "https://altered-prod-eu.s3.amazonaws.com/Art/DUSTEROP/CARDS/ALT_DUSTEROP_A_AX_98/JPG/fr_FR/8bbf0fee9275f54ed030a8cef1eea9de.jpg",
      "en-us": "https://altered-prod-eu.s3.amazonaws.com/Art/DUSTEROP/CARDS/ALT_DUSTEROP_A_AX_98/JPG/en_US/29d4d0dd1b6f64ae9b43aa0047a7099a.jpg",
      "it-it": "",
      "es-es": "",
      "de-de": ""
    },
    "name": "Technological Encounter",
    "elements": {
      "MAIN_COST": "4",
      "RECALL_COST": "2",
      "MAIN_EFFECT": "[Cooldown].  Draw a card, then create a [Manaseed] token in your Landmarks."
    },
    "isSuspended": false,
    "isErrated": false,
    "isBanned": false,
    "isSerialized": false,
    "isParentSerialized": false,
    "collectorNumber": "SDUOP-014-C-EN"
  },
  {
    "@context": "/contexts/Card",
    "@id": "/cards/ALT_DUSTEROP_A_AX_98_R1",
    "@type": "Card",
    "cardType": {
      "@id": "/card_types/01GE7AC9X35JXEQZJBBD6E4BKX",
      "@type": "CardType",
      "reference": "SPELL",
      "id": "01GE7AC9X35JXEQZJBBD6E4BKX",
      "name": "Spell"
    },
    "cardSubTypes": [
      {
        "@type": "CardSubType",
        "@id": "/.well-known/genid/e3cfd0605d6bb0b4642c",
        "reference": "CONJURATION",
        "id": "01HKAGQJMGEVS21MCGWDGG8KW0",
        "name": "Conjuration"
      },
      {
        "@type": "CardSubType",
        "@id": "/.well-known/genid/7670181e6185363826ca",
        "reference": "MANEUVER",
        "id": "01HKAGPGT0M24AWMMF30CN0NT4",
        "name": "Maneuver"
      }
    ],
    "cardSet": {
      "@id": "/card_sets/DUSTEROP",
      "@type": "CardSet",
      "id": "01K4YGEBN10S3MMN6J9CW5B4AC",
      "reference": "DUSTEROP",
      "name": "Seeds of Unity - Organized Play"
    },
    "rarity": {
      "@type": "Rarity",
      "@id": "/.well-known/genid/bf8ef613054a8fcaa913",
      "reference": "RARE",
      "id": "01GE7AC9WY6PK56RADXXD6P1T5",
      "name": "Rare"
    },
    "imagePath": "https://altered-prod-eu.s3.amazonaws.com/Art/DUSTEROP/CARDS/ALT_DUSTEROP_A_AX_98/JPG/en_US/89d7f47aacaa015b0ff4c653a094006d.jpg",
    "assets": {
      "WEB": [
        "https://altered-prod-eu.s3.amazonaws.com/Art/DUSTEROP/CARDS/ALT_DUSTEROP_A_AX_98/WEB_3bf03c8d4b745653df54077fc17339e7",
        "https://altered-prod-eu.s3.amazonaws.com/Art/DUSTEROP/CARDS/ALT_DUSTEROP_A_AX_98/WEB_31fa15d61fa8a2f1869d8fce838a0cdd"
      ]
    },
    "lowerPrice": 0,
    "qrUrlDetail": "https://qr.altered.gg/ALT_DUSTEROP_A_AX_98_R1",
    "isOwnerless": false,
    "reference": "ALT_DUSTEROP_A_AX_98_R1",
    "id": "01K4YGECGRVP002XYTEWX1RAJX",
    "mainFaction": {
      "@id": "/factions/AX",
      "@type": "Faction",
      "reference": "AX",
      "color": "#8c432a",
      "id": "01GE7AC9XBG707G19F03A95TH1",
      "name": "Axiom"
    },
    "allImagePath": {
      "fr-fr": "https://altered-prod-eu.s3.amazonaws.com/Art/DUSTEROP/CARDS/ALT_DUSTEROP_A_AX_98/JPG/fr_FR/0f9cf1ebcb3c45687cca714bd4d1f8c0.jpg",
      "en-us": "https://altered-prod-eu.s3.amazonaws.com/Art/DUSTEROP/CARDS/ALT_DUSTEROP_A_AX_98/JPG/en_US/89d7f47aacaa015b0ff4c653a094006d.jpg",
      "it-it": "",
      "es-es": "",
      "de-de": ""
    },
    "name": "Technological Encounter",
    "elements": {
      "MAIN_COST": "#3#",
      "RECALL_COST": "2",
      "MAIN_EFFECT": "[Cooldown].  Draw a card, then create a [Manaseed] token in your Landmarks."
    },
    "isSuspended": false,
    "isErrated": false,
    "isBanned": false,
    "isSerialized": false,
    "isParentSerialized": false,
    "collectorNumber": "SDUOP-014-R-EN"
  },
  {
    "@context": "/contexts/Card",
    "@id": "/cards/ALT_DUSTEROP_A_BR_99_R2",
    "@type": "Card",
    "cardType": {
      "@id": "/card_types/01GE7AC9X35JXEQZJBBD6E4BKX",
      "@type": "CardType",
      "reference": "SPELL",
      "id": "01GE7AC9X35JXEQZJBBD6E4BKX",
      "name": "Spell"
    },
    "cardSubTypes": [
      {
        "@type": "CardSubType",
        "@id": "/.well-known/genid/3e78250ee7e819721ca9",
        "reference": "MANEUVER",
        "id": "01HKAGPGT0M24AWMMF30CN0NT4",
        "name": "Maneuver"
      }
    ],
    "cardSet": {
      "@id": "/card_sets/DUSTEROP",
      "@type": "CardSet",
      "id": "01K4YGEBN10S3MMN6J9CW5B4AC",
      "reference": "DUSTEROP",
      "name": "Seeds of Unity - Organized Play"
    },
    "rarity": {
      "@type": "Rarity",
      "@id": "/.well-known/genid/c0e7f70a1ca70795f93e",
      "reference": "RARE",
      "id": "01GE7AC9WY6PK56RADXXD6P1T5",
      "name": "Rare"
    },
    "imagePath": "https://altered-prod-eu.s3.amazonaws.com/Art/DUSTEROP/CARDS/ALT_DUSTEROP_A_BR_99/JPG/en_US/a28de82102eb87b3331aacdf05a7d399.jpg",
    "assets": {
      "WEB": [
        "https://altered-prod-eu.s3.amazonaws.com/Art/DUSTEROP/CARDS/ALT_DUSTEROP_A_BR_99/WEB_afbeab4ba3222731ba48ed95673e8006",
        "https://altered-prod-eu.s3.amazonaws.com/Art/DUSTEROP/CARDS/ALT_DUSTEROP_A_BR_99/WEB_b0af19e4f3a64ff05e065830a8d7dc80"
      ]
    },
    "lowerPrice": 0,
    "qrUrlDetail": "https://qr.altered.gg/ALT_DUSTEROP_A_BR_99_R2",
    "isOwnerless": false,
    "reference": "ALT_DUSTEROP_A_BR_99_R2",
    "id": "01K4YGECGVR8KHDVDJ345YYJ15",
    "mainFaction": {
      "@id": "/factions/AX",
      "@type": "Faction",
      "reference": "AX",
      "color": "#8c432a",
      "id": "01GE7AC9XBG707G19F03A95TH1",
      "name": "Axiom"
    },
    "allImagePath": {
      "fr-fr": "https://altered-prod-eu.s3.amazonaws.com/Art/DUSTEROP/CARDS/ALT_DUSTEROP_A_BR_99/JPG/fr_FR/7d6c7be1b79963b2d611d4d723c97cda.jpg",
      "en-us": "https://altered-prod-eu.s3.amazonaws.com/Art/DUSTEROP/CARDS/ALT_DUSTEROP_A_BR_99/JPG/en_US/a28de82102eb87b3331aacdf05a7d399.jpg",
      "it-it": "",
      "es-es": "",
      "de-de": ""
    },
    "name": "Market Encounter",
    "elements": {
      "MAIN_COST": "2",
      "RECALL_COST": "2",
      "MAIN_EFFECT": "Create a [Manaseed] token in your Landmarks.",
      "ECHO_EFFECT": "{D} : The next Character played from your hand this turn activates one of its {r} abilities."
    },
    "isSuspended": false,
    "isErrated": false,
    "isBanned": false,
    "isSerialized": false,
    "isParentSerialized": false,
    "collectorNumber": "SOUOP-015-F-EN"
  },
  {
    "@context": "/contexts/Card",
    "@id": "/cards/ALT_DUSTEROP_P_BR_95_C",
    "@type": "Card",
    "cardType": {
      "@id": "/card_types/01H19NWA92A4ERAC4ATMSZNASS",
      "@type": "CardType",
      "reference": "CHARACTER",
      "id": "01H19NWA92A4ERAC4ATMSZNASS",
      "name": "Character"
    },
    "cardSubTypes": [
      {
        "@type": "CardSubType",
        "@id": "/.well-known/genid/f161a9b63362fd6067ec",
        "reference": "TRAINER",
        "id": "01HKAGQ07R8R2DAC69RKNZ5SA6",
        "name": "Trainer"
      }
    ],
    "cardSet": {
      "@id": "/card_sets/DUSTEROP",
      "@type": "CardSet",
      "id": "01K4YGEBN10S3MMN6J9CW5B4AC",
      "reference": "DUSTEROP",
      "name": "Seeds of Unity - Organized Play"
    },
    "rarity": {
      "@type": "Rarity",
      "@id": "/.well-known/genid/e3dc530bc8a57fa69e37",
      "reference": "COMMON",
      "id": "01GE7AC9WEQKW1Y1BF8SCY745A",
      "name": "Common"
    },
    "imagePath": "https://altered-prod-eu.s3.amazonaws.com/Art/DUSTEROP/CARDS/ALT_DUSTEROP_P_BR_95/JPG/en_US/a101150bb6dcfbd707775ed98a6e41d2.jpg",
    "assets": {
      "WEB": [
        "https://altered-prod-eu.s3.amazonaws.com/Art/DUSTEROP/CARDS/ALT_DUSTEROP_P_BR_95/WEB_b85b50e4d4d6e7b7a8ef37c00f886df9",
        "https://altered-prod-eu.s3.amazonaws.com/Art/DUSTEROP/CARDS/ALT_DUSTEROP_P_BR_95/WEB_b5e9f8330b4984aaed6f02036d7dd0bc",
        "https://altered-prod-eu.s3.amazonaws.com/Art/DUSTEROP/CARDS/ALT_DUSTEROP_P_BR_95/WEB_50c8635f95a600850777af6a79a781a3"
      ]
    },
    "lowerPrice": 0,
    "qrUrlDetail": "https://qr.altered.gg/ALT_DUSTEROP_P_BR_95_C",
    "isOwnerless": false,
    "reference": "ALT_DUSTEROP_P_BR_95_C",
    "id": "01K4YGECGTNVYF1A49CQHT1JPY",
    "mainFaction": {
      "@id": "/factions/BR",
      "@type": "Faction",
      "reference": "BR",
      "color": "#c32637",
      "id": "01GE7AC9WY6PK56RADXXD6P1T4",
      "name": "Bravos"
    },
    "allImagePath": {
      "fr-fr": "https://altered-prod-eu.s3.amazonaws.com/Art/DUSTEROP/CARDS/ALT_DUSTEROP_P_BR_95/JPG/fr_FR/2b620fae222110bcb8bf8130de31884f.jpg",
      "en-us": "https://altered-prod-eu.s3.amazonaws.com/Art/DUSTEROP/CARDS/ALT_DUSTEROP_P_BR_95/JPG/en_US/a101150bb6dcfbd707775ed98a6e41d2.jpg",
      "it-it": "",
      "es-es": "",
      "de-de": ""
    },
    "name": "Deep-Cloud Instructor",
    "elements": {
      "MAIN_COST": "2",
      "RECALL_COST": "4",
      "OCEAN_POWER": "1",
      "FOREST_POWER": "1",
      "MOUNTAIN_POWER": "3",
      "MAIN_EFFECT": "{H} You may [Rush] a Character. If played from your hand, it activates one of its {r} abilities.  {R} Ottengo 2 rinforzi."
    },
    "isSuspended": false,
    "isErrated": false,
    "isBanned": false,
    "isSerialized": false,
    "isParentSerialized": false,
    "collectorNumber": "SDUOP-002-C-EN"
  },
  {
    "@context": "/contexts/Card",
    "@id": "/cards/ALT_DUSTEROP_P_BR_94_R1",
    "@type": "Card",
    "cardType": {
      "@id": "/card_types/01H19NWA92A4ERAC4ATMSZNASS",
      "@type": "CardType",
      "reference": "CHARACTER",
      "id": "01H19NWA92A4ERAC4ATMSZNASS",
      "name": "Character"
    },
    "cardSubTypes": [
      {
        "@type": "CardSubType",
        "@id": "/.well-known/genid/efc811417b6fd98b6ceb",
        "reference": "CITIZEN",
        "id": "01HKAGQWDFDGS8YVZGW98BVV9D",
        "name": "Citizen"
      }
    ],
    "cardSet": {
      "@id": "/card_sets/DUSTEROP",
      "@type": "CardSet",
      "id": "01K4YGEBN10S3MMN6J9CW5B4AC",
      "reference": "DUSTEROP",
      "name": "Seeds of Unity - Organized Play"
    },
    "rarity": {
      "@type": "Rarity",
      "@id": "/.well-known/genid/b86bc1a9a07e08f913a1",
      "reference": "RARE",
      "id": "01GE7AC9WY6PK56RADXXD6P1T5",
      "name": "Rare"
    },
    "imagePath": "https://altered-prod-eu.s3.amazonaws.com/Art/DUSTEROP/CARDS/ALT_DUSTEROP_P_BR_94/JPG/en_US/09b8f82d9afbcc0d445536c35c82f69b.jpg",
    "assets": {
      "WEB": [
        "https://altered-prod-eu.s3.amazonaws.com/Art/DUSTEROP/CARDS/ALT_DUSTEROP_P_BR_94/WEB_91596123d59f294dbbeb9aff581cd127",
        "https://altered-prod-eu.s3.amazonaws.com/Art/DUSTEROP/CARDS/ALT_DUSTEROP_P_BR_94/WEB_3828768266179e92715d2ffd967a3c9f",
        "https://altered-prod-eu.s3.amazonaws.com/Art/DUSTEROP/CARDS/ALT_DUSTEROP_P_BR_94/WEB_fae33cab4f78c1272d1d680e165016e4"
      ]
    },
    "lowerPrice": 0,
    "qrUrlDetail": "https://qr.altered.gg/ALT_DUSTEROP_P_BR_94_R1",
    "isOwnerless": false,
    "reference": "ALT_DUSTEROP_P_BR_94_R1",
    "id": "01K4YGECGVR8KHDVDJ345YYJ0S",
    "mainFaction": {
      "@id": "/factions/BR",
      "@type": "Faction",
      "reference": "BR",
      "color": "#c32637",
      "id": "01GE7AC9WY6PK56RADXXD6P1T4",
      "name": "Bravos"
    },
    "allImagePath": {
      "fr-fr": "https://altered-prod-eu.s3.amazonaws.com/Art/DUSTEROP/CARDS/ALT_DUSTEROP_P_BR_94/JPG/fr_FR/5ccfbe6df152a9a562cc5ecb54376d35.jpg",
      "en-us": "https://altered-prod-eu.s3.amazonaws.com/Art/DUSTEROP/CARDS/ALT_DUSTEROP_P_BR_94/JPG/en_US/09b8f82d9afbcc0d445536c35c82f69b.jpg",
      "it-it": "",
      "es-es": "",
      "de-de": ""
    },
    "name": "Reka Fisherman",
    "elements": {
      "MAIN_COST": "3",
      "RECALL_COST": "5",
      "OCEAN_POWER": "4",
      "FOREST_POWER": "#3#",
      "MOUNTAIN_POWER": "#3#",
      "MAIN_EFFECT": "#{R} Draw a card.#  {R} Create two [Manaseed] tokens in your Landmarks."
    },
    "isSuspended": false,
    "isErrated": false,
    "isBanned": false,
    "isSerialized": false,
    "isParentSerialized": false,
    "collectorNumber": "SDUOP-008-R-EN"
  },
  {
    "@context": "/contexts/Card",
    "@id": "/cards/ALT_DUSTEROP_A_BR_99_C",
    "@type": "Card",
    "cardType": {
      "@id": "/card_types/01GE7AC9X35JXEQZJBBD6E4BKX",
      "@type": "CardType",
      "reference": "SPELL",
      "id": "01GE7AC9X35JXEQZJBBD6E4BKX",
      "name": "Spell"
    },
    "cardSubTypes": [
      {
        "@type": "CardSubType",
        "@id": "/.well-known/genid/654320395b97ba833f9c",
        "reference": "MANEUVER",
        "id": "01HKAGPGT0M24AWMMF30CN0NT4",
        "name": "Maneuver"
      }
    ],
    "cardSet": {
      "@id": "/card_sets/DUSTEROP",
      "@type": "CardSet",
      "id": "01K4YGEBN10S3MMN6J9CW5B4AC",
      "reference": "DUSTEROP",
      "name": "Seeds of Unity - Organized Play"
    },
    "rarity": {
      "@type": "Rarity",
      "@id": "/.well-known/genid/8306beef40df1203c103",
      "reference": "COMMON",
      "id": "01GE7AC9WEQKW1Y1BF8SCY745A",
      "name": "Common"
    },
    "imagePath": "https://altered-prod-eu.s3.amazonaws.com/Art/DUSTEROP/CARDS/ALT_DUSTEROP_A_BR_99/JPG/en_US/fcd5dafc19a332825e8de3540ec3eb42.jpg",
    "assets": {
      "WEB": [
        "https://altered-prod-eu.s3.amazonaws.com/Art/DUSTEROP/CARDS/ALT_DUSTEROP_A_BR_99/WEB_afbeab4ba3222731ba48ed95673e8006",
        "https://altered-prod-eu.s3.amazonaws.com/Art/DUSTEROP/CARDS/ALT_DUSTEROP_A_BR_99/WEB_b0af19e4f3a64ff05e065830a8d7dc80"
      ]
    },
    "lowerPrice": 0,
    "qrUrlDetail": "https://qr.altered.gg/ALT_DUSTEROP_A_BR_99_C",
    "isOwnerless": false,
    "reference": "ALT_DUSTEROP_A_BR_99_C",
    "id": "01K4YGECGVR8KHDVDJ345YYJ0Z",
    "mainFaction": {
      "@id": "/factions/BR",
      "@type": "Faction",
      "reference": "BR",
      "color": "#c32637",
      "id": "01GE7AC9WY6PK56RADXXD6P1T4",
      "name": "Bravos"
    },
    "allImagePath": {
      "fr-fr": "https://altered-prod-eu.s3.amazonaws.com/Art/DUSTEROP/CARDS/ALT_DUSTEROP_A_BR_99/JPG/fr_FR/2c6229f7bed000cc33692b5f89821acf.jpg",
      "en-us": "https://altered-prod-eu.s3.amazonaws.com/Art/DUSTEROP/CARDS/ALT_DUSTEROP_A_BR_99/JPG/en_US/fcd5dafc19a332825e8de3540ec3eb42.jpg",
      "it-it": "",
      "es-es": "",
      "de-de": ""
    },
    "name": "Market Encounter",
    "elements": {
      "MAIN_COST": "2",
      "RECALL_COST": "2",
      "MAIN_EFFECT": "Create a [Manaseed] token in your Landmarks.",
      "ECHO_EFFECT": "{D} : The next Character played from your hand this turn activates one of its {r} abilities."
    },
    "isSuspended": false,
    "isErrated": false,
    "isBanned": false,
    "isSerialized": false,
    "isParentSerialized": false,
    "collectorNumber": "SDUOP-015-C-EN"
  },
  {
    "@context": "/contexts/Card",
    "@id": "/cards/ALT_DUSTEROP_A_BR_99_R1",
    "@type": "Card",
    "cardType": {
      "@id": "/card_types/01GE7AC9X35JXEQZJBBD6E4BKX",
      "@type": "CardType",
      "reference": "SPELL",
      "id": "01GE7AC9X35JXEQZJBBD6E4BKX",
      "name": "Spell"
    },
    "cardSubTypes": [
      {
        "@type": "CardSubType",
        "@id": "/.well-known/genid/31527f036c53ddee39b6",
        "reference": "MANEUVER",
        "id": "01HKAGPGT0M24AWMMF30CN0NT4",
        "name": "Maneuver"
      }
    ],
    "cardSet": {
      "@id": "/card_sets/DUSTEROP",
      "@type": "CardSet",
      "id": "01K4YGEBN10S3MMN6J9CW5B4AC",
      "reference": "DUSTEROP",
      "name": "Seeds of Unity - Organized Play"
    },
    "rarity": {
      "@type": "Rarity",
      "@id": "/.well-known/genid/03ad314fd5858fd8aa7d",
      "reference": "RARE",
      "id": "01GE7AC9WY6PK56RADXXD6P1T5",
      "name": "Rare"
    },
    "imagePath": "https://altered-prod-eu.s3.amazonaws.com/Art/DUSTEROP/CARDS/ALT_DUSTEROP_A_BR_99/JPG/en_US/1554f5781913dbe1ea2116b896229f25.jpg",
    "assets": {
      "WEB": [
        "https://altered-prod-eu.s3.amazonaws.com/Art/DUSTEROP/CARDS/ALT_DUSTEROP_A_BR_99/WEB_afbeab4ba3222731ba48ed95673e8006",
        "https://altered-prod-eu.s3.amazonaws.com/Art/DUSTEROP/CARDS/ALT_DUSTEROP_A_BR_99/WEB_b0af19e4f3a64ff05e065830a8d7dc80"
      ]
    },
    "lowerPrice": 0,
    "qrUrlDetail": "https://qr.altered.gg/ALT_DUSTEROP_A_BR_99_R1",
    "isOwnerless": false,
    "reference": "ALT_DUSTEROP_A_BR_99_R1",
    "id": "01K4YGECGVR8KHDVDJ345YYJ12",
    "mainFaction": {
      "@id": "/factions/BR",
      "@type": "Faction",
      "reference": "BR",
      "color": "#c32637",
      "id": "01GE7AC9WY6PK56RADXXD6P1T4",
      "name": "Bravos"
    },
    "allImagePath": {
      "fr-fr": "https://altered-prod-eu.s3.amazonaws.com/Art/DUSTEROP/CARDS/ALT_DUSTEROP_A_BR_99/JPG/fr_FR/af35b8acdbd3ca42eb6cede3f4f7c556.jpg",
      "en-us": "https://altered-prod-eu.s3.amazonaws.com/Art/DUSTEROP/CARDS/ALT_DUSTEROP_A_BR_99/JPG/en_US/1554f5781913dbe1ea2116b896229f25.jpg",
      "it-it": "",
      "es-es": "",
      "de-de": ""
    },
    "name": "Market Encounter",
    "elements": {
      "MAIN_COST": "#3#",
      "RECALL_COST": "#4#",
      "MAIN_EFFECT": "#Put the top card of your deck in your Mana zone (as an exhausted Mana Orb).#",
      "ECHO_EFFECT": "{D} : The next Character played from your hand this turn activates one of its {r} abilities."
    },
    "isSuspended": false,
    "isErrated": false,
    "isBanned": false,
    "isSerialized": false,
    "isParentSerialized": false,
    "collectorNumber": "SDUOP-015-R-EN"
  },
  {
    "@context": "/contexts/Card",
    "@id": "/cards/ALT_DUSTEROP_A_YZ_97_R2",
    "@type": "Card",
    "cardType": {
      "@id": "/card_types/01GE7AC9X35JXEQZJBBD6E4BKX",
      "@type": "CardType",
      "reference": "SPELL",
      "id": "01GE7AC9X35JXEQZJBBD6E4BKX",
      "name": "Spell"
    },
    "cardSubTypes": [
      {
        "@type": "CardSubType",
        "@id": "/.well-known/genid/caa78f498f9c5ee1d139",
        "reference": "BOON",
        "id": "01HKAGPHVVK20XKBXKCZNGRTFD",
        "name": "Boon"
      },
      {
        "@type": "CardSubType",
        "@id": "/.well-known/genid/bab955a749429b2aba3d",
        "reference": "MANEUVER",
        "id": "01HKAGPGT0M24AWMMF30CN0NT4",
        "name": "Maneuver"
      }
    ],
    "cardSet": {
      "@id": "/card_sets/DUSTEROP",
      "@type": "CardSet",
      "id": "01K4YGEBN10S3MMN6J9CW5B4AC",
      "reference": "DUSTEROP",
      "name": "Seeds of Unity - Organized Play"
    },
    "rarity": {
      "@type": "Rarity",
      "@id": "/.well-known/genid/3a13ac79e8d73d459954",
      "reference": "RARE",
      "id": "01GE7AC9WY6PK56RADXXD6P1T5",
      "name": "Rare"
    },
    "imagePath": "https://altered-prod-eu.s3.amazonaws.com/Art/DUSTEROP/CARDS/ALT_DUSTEROP_A_YZ_97/JPG/en_US/3ba464afded5a1a39843aa0c4caaa05b.jpg",
    "assets": {
      "WEB": [
        "https://altered-prod-eu.s3.amazonaws.com/Art/DUSTEROP/CARDS/ALT_DUSTEROP_A_YZ_97/WEB_2e7c7af59dda181e0d940fd32adebb2b",
        "https://altered-prod-eu.s3.amazonaws.com/Art/DUSTEROP/CARDS/ALT_DUSTEROP_A_YZ_97/WEB_13dc7089e63dfd3469017779459c3194"
      ]
    },
    "lowerPrice": 0,
    "qrUrlDetail": "https://qr.altered.gg/ALT_DUSTEROP_A_YZ_97_R2",
    "isOwnerless": false,
    "reference": "ALT_DUSTEROP_A_YZ_97_R2",
    "id": "01K4YGECH75K3EB7FWR6TF39QC",
    "mainFaction": {
      "@id": "/factions/BR",
      "@type": "Faction",
      "reference": "BR",
      "color": "#c32637",
      "id": "01GE7AC9WY6PK56RADXXD6P1T4",
      "name": "Bravos"
    },
    "allImagePath": {
      "fr-fr": "https://altered-prod-eu.s3.amazonaws.com/Art/DUSTEROP/CARDS/ALT_DUSTEROP_A_YZ_97/JPG/fr_FR/e51ba5ea3a11be36b04e603ee4ce92a7.jpg",
      "en-us": "https://altered-prod-eu.s3.amazonaws.com/Art/DUSTEROP/CARDS/ALT_DUSTEROP_A_YZ_97/JPG/en_US/3ba464afded5a1a39843aa0c4caaa05b.jpg",
      "it-it": "",
      "es-es": "",
      "de-de": ""
    },
    "name": "Sports Encounter",
    "elements": {
      "MAIN_COST": "2",
      "RECALL_COST": "#1#",
      "MAIN_EFFECT": "#[Cooldown].#  Distribute 2 boosts among any target Characters in play #or in Reserve.#",
      "ECHO_EFFECT": "{D}: [After You]."
    },
    "isSuspended": false,
    "isErrated": false,
    "isBanned": false,
    "isSerialized": false,
    "isParentSerialized": false,
    "collectorNumber": "SDUOP-019-F-EN"
  },
  {
    "@context": "/contexts/Card",
    "@id": "/cards/ALT_DUSTEROP_B_BR_31_C",
    "@type": "Card",
    "cardType": {
      "@id": "/card_types/01H0FV1VGP26CD3DFE8W3PWTQT",
      "@type": "CardType",
      "reference": "TOKEN",
      "id": "01H0FV1VGP26CD3DFE8W3PWTQT",
      "name": "Token Character"
    },
    "cardSubTypes": [
      {
        "@type": "CardSubType",
        "@id": "/.well-known/genid/8630678db1b67b7f6752",
        "reference": "COMPANION",
        "id": "01HKAGQPYTEKRYT4PRE9HZHTDA",
        "name": "Companion"
      }
    ],
    "cardSet": {
      "@id": "/card_sets/DUSTEROP",
      "@type": "CardSet",
      "id": "01K4YGEBN10S3MMN6J9CW5B4AC",
      "reference": "DUSTEROP",
      "name": "Seeds of Unity - Organized Play"
    },
    "rarity": {
      "@type": "Rarity",
      "@id": "/.well-known/genid/f4292bd85acead942309",
      "reference": "COMMON",
      "id": "01GE7AC9WEQKW1Y1BF8SCY745A",
      "name": "Common"
    },
    "imagePath": "https://altered-prod-eu.s3.amazonaws.com/Art/DUSTEROP/CARDS/ALT_DUSTEROP_B_BR_31/JPG/en_US/35387d9175c66957f4e80618ff13d43f.jpg",
    "assets": {
      "WEB": [
        "https://altered-prod-eu.s3.amazonaws.com/Art/DUSTEROP/CARDS/ALT_DUSTEROP_B_BR_31/WEB_004629ecf15822ea23536c47fa674e09"
      ]
    },
    "lowerPrice": 0,
    "qrUrlDetail": "https://qr.altered.gg/ALT_DUSTEROP_B_BR_31_C",
    "isOwnerless": true,
    "reference": "ALT_DUSTEROP_B_BR_31_C",
    "id": "01K8NQYDYZFEJ4MK8ZT7K4GX3C",
    "mainFaction": {
      "@id": "/factions/BR",
      "@type": "Faction",
      "reference": "BR",
      "color": "#c32637",
      "id": "01GE7AC9WY6PK56RADXXD6P1T4",
      "name": "Bravos"
    },
    "allImagePath": {
      "fr-fr": "https://altered-prod-eu.s3.amazonaws.com/Art/DUSTEROP/CARDS/ALT_DUSTEROP_B_BR_31/JPG/fr_FR/cdae7441275e5e38bc8a3ed319b179ca.jpg",
      "en-us": "https://altered-prod-eu.s3.amazonaws.com/Art/DUSTEROP/CARDS/ALT_DUSTEROP_B_BR_31/JPG/en_US/35387d9175c66957f4e80618ff13d43f.jpg",
      "it-it": "https://altered-prod-eu.s3.amazonaws.com/Art/DUSTEROP/CARDS/ALT_DUSTEROP_B_BR_31/JPG/it_IT/4da2632638b850bff4b391669b91c981.jpg",
      "es-es": "https://altered-prod-eu.s3.amazonaws.com/Art/DUSTEROP/CARDS/ALT_DUSTEROP_B_BR_31/JPG/es_ES/11b94f8b4561b96b93d8cdcb10b47628.jpg",
      "de-de": "https://altered-prod-eu.s3.amazonaws.com/Art/DUSTEROP/CARDS/ALT_DUSTEROP_B_BR_31/JPG/de_DE/2335be934518812a02696b1c4a677326.jpg"
    },
    "name": "Booda",
    "elements": {
      "MAIN_COST": "0",
      "RECALL_COST": "0",
      "OCEAN_POWER": "2",
      "MOUNTAIN_POWER": "2",
      "FOREST_POWER": "2"
    },
    "isSuspended": false,
    "isErrated": false,
    "isBanned": false,
    "isSerialized": false,
    "isParentSerialized": false,
    "collectorNumber": "SDUOP-022-T-EN"
  },
  {
    "@context": "/contexts/Card",
    "@id": "/cards/ALT_DUSTEROP_P_LY_87_C",
    "@type": "Card",
    "cardType": {
      "@id": "/card_types/01H19NWA92A4ERAC4ATMSZNASS",
      "@type": "CardType",
      "reference": "CHARACTER",
      "id": "01H19NWA92A4ERAC4ATMSZNASS",
      "name": "Character"
    },
    "cardSubTypes": [
      {
        "@type": "CardSubType",
        "@id": "/.well-known/genid/9ce36f984cd02c7bbf8e",
        "reference": "CITIZEN",
        "id": "01HKAGQWDFDGS8YVZGW98BVV9D",
        "name": "Citizen"
      }
    ],
    "cardSet": {
      "@id": "/card_sets/DUSTEROP",
      "@type": "CardSet",
      "id": "01K4YGEBN10S3MMN6J9CW5B4AC",
      "reference": "DUSTEROP",
      "name": "Seeds of Unity - Organized Play"
    },
    "rarity": {
      "@type": "Rarity",
      "@id": "/.well-known/genid/1e37fc989e01eae84092",
      "reference": "COMMON",
      "id": "01GE7AC9WEQKW1Y1BF8SCY745A",
      "name": "Common"
    },
    "imagePath": "https://altered-prod-eu.s3.amazonaws.com/Art/DUSTEROP/CARDS/ALT_DUSTEROP_P_LY_87/JPG/en_US/026ea040b5f9d76eddd18f5b97ea46e4.jpg",
    "assets": {
      "WEB": [
        "https://altered-prod-eu.s3.amazonaws.com/Art/DUSTEROP/CARDS/ALT_DUSTEROP_P_LY_87/WEB_3def63fd4f71e19155c9ab1778b1a453",
        "https://altered-prod-eu.s3.amazonaws.com/Art/DUSTEROP/CARDS/ALT_DUSTEROP_P_LY_87/WEB_46cdc5a82582519a48465523f7e3ec81",
        "https://altered-prod-eu.s3.amazonaws.com/Art/DUSTEROP/CARDS/ALT_DUSTEROP_P_LY_87/WEB_ab973cc46a201c7dead41627e82d59fb"
      ]
    },
    "lowerPrice": 0,
    "qrUrlDetail": "https://qr.altered.gg/ALT_DUSTEROP_P_LY_87_C",
    "isOwnerless": false,
    "reference": "ALT_DUSTEROP_P_LY_87_C",
    "id": "01K4YGECGXZMF34SHDVQ6H347Z",
    "mainFaction": {
      "@id": "/factions/LY",
      "@type": "Faction",
      "reference": "LY",
      "color": "#cf4171",
      "id": "01GE7AC9XGB6JE2V63WXWN4FB3",
      "name": "Lyra"
    },
    "allImagePath": {
      "fr-fr": "https://altered-prod-eu.s3.amazonaws.com/Art/DUSTEROP/CARDS/ALT_DUSTEROP_P_LY_87/JPG/fr_FR/2d57ad72fb1f6f2347963422a5d3286b.jpg",
      "en-us": "https://altered-prod-eu.s3.amazonaws.com/Art/DUSTEROP/CARDS/ALT_DUSTEROP_P_LY_87/JPG/en_US/026ea040b5f9d76eddd18f5b97ea46e4.jpg",
      "it-it": "",
      "es-es": "",
      "de-de": ""
    },
    "name": "Reka Guide",
    "elements": {
      "MAIN_COST": "2",
      "RECALL_COST": "2",
      "OCEAN_POWER": "1",
      "FOREST_POWER": "2",
      "MOUNTAIN_POWER": "2",
      "ECHO_EFFECT": "{D} : Return another Character from your Reserve to your hand."
    },
    "isSuspended": false,
    "isErrated": false,
    "isBanned": false,
    "isSerialized": false,
    "isParentSerialized": false,
    "collectorNumber": "SDUOP-003-C-EN"
  },
  {
    "@context": "/contexts/Card",
    "@id": "/cards/ALT_DUSTEROP_P_LY_94_R1",
    "@type": "Card",
    "cardType": {
      "@id": "/card_types/01H19NWA92A4ERAC4ATMSZNASS",
      "@type": "CardType",
      "reference": "CHARACTER",
      "id": "01H19NWA92A4ERAC4ATMSZNASS",
      "name": "Character"
    },
    "cardSubTypes": [
      {
        "@type": "CardSubType",
        "@id": "/.well-known/genid/00924f3b0b68ada465a0",
        "reference": "CITIZEN",
        "id": "01HKAGQWDFDGS8YVZGW98BVV9D",
        "name": "Citizen"
      }
    ],
    "cardSet": {
      "@id": "/card_sets/DUSTEROP",
      "@type": "CardSet",
      "id": "01K4YGEBN10S3MMN6J9CW5B4AC",
      "reference": "DUSTEROP",
      "name": "Seeds of Unity - Organized Play"
    },
    "rarity": {
      "@type": "Rarity",
      "@id": "/.well-known/genid/5c23be2fbe5641286c99",
      "reference": "RARE",
      "id": "01GE7AC9WY6PK56RADXXD6P1T5",
      "name": "Rare"
    },
    "imagePath": "https://altered-prod-eu.s3.amazonaws.com/Art/DUSTEROP/CARDS/ALT_DUSTEROP_P_LY_94/JPG/en_US/f41a1908268212c5035e4210a5e94765.jpg",
    "assets": {
      "WEB": [
        "https://altered-prod-eu.s3.amazonaws.com/Art/DUSTEROP/CARDS/ALT_DUSTEROP_P_LY_94/WEB_92687b5e03b4f6de17bdb43e1ad773d3",
        "https://altered-prod-eu.s3.amazonaws.com/Art/DUSTEROP/CARDS/ALT_DUSTEROP_P_LY_94/WEB_73ea2a25d9b8dd7da78a09ab7277437c",
        "https://altered-prod-eu.s3.amazonaws.com/Art/DUSTEROP/CARDS/ALT_DUSTEROP_P_LY_94/WEB_905f146916579072324a60c42eb9991d"
      ]
    },
    "lowerPrice": 0,
    "qrUrlDetail": "https://qr.altered.gg/ALT_DUSTEROP_P_LY_94_R1",
    "isOwnerless": false,
    "reference": "ALT_DUSTEROP_P_LY_94_R1",
    "id": "01K4YGECGY9XSJBXPCXRG95JYX",
    "mainFaction": {
      "@id": "/factions/LY",
      "@type": "Faction",
      "reference": "LY",
      "color": "#cf4171",
      "id": "01GE7AC9XGB6JE2V63WXWN4FB3",
      "name": "Lyra"
    },
    "allImagePath": {
      "fr-fr": "https://altered-prod-eu.s3.amazonaws.com/Art/DUSTEROP/CARDS/ALT_DUSTEROP_P_LY_94/JPG/fr_FR/ec3b1a8456c0ae2f58a89b259844ce77.jpg",
      "en-us": "https://altered-prod-eu.s3.amazonaws.com/Art/DUSTEROP/CARDS/ALT_DUSTEROP_P_LY_94/JPG/en_US/f41a1908268212c5035e4210a5e94765.jpg",
      "it-it": "",
      "es-es": "",
      "de-de": ""
    },
    "name": "Nightclub Bouncer",
    "elements": {
      "MAIN_COST": "3",
      "RECALL_COST": "3",
      "OCEAN_POWER": "4",
      "FOREST_POWER": "4",
      "MOUNTAIN_POWER": "0",
      "MAIN_EFFECT": "#{J}# If I'm [In Contact], [Sabotage]. #Otherwise, you may exhaust target card in Reserve.#"
    },
    "isSuspended": false,
    "isErrated": false,
    "isBanned": false,
    "isSerialized": false,
    "isParentSerialized": false,
    "collectorNumber": "SDUOP-009-R-EN"
  },
  {
    "@context": "/contexts/Card",
    "@id": "/cards/ALT_DUSTEROP_A_LY_100_C",
    "@type": "Card",
    "cardType": {
      "@id": "/card_types/01GE7AC9X35JXEQZJBBD6E4BKX",
      "@type": "CardType",
      "reference": "SPELL",
      "id": "01GE7AC9X35JXEQZJBBD6E4BKX",
      "name": "Spell"
    },
    "cardSubTypes": [
      {
        "@type": "CardSubType",
        "@id": "/.well-known/genid/fc0f690e4a5a75e22eb7",
        "reference": "MANEUVER",
        "id": "01HKAGPGT0M24AWMMF30CN0NT4",
        "name": "Maneuver"
      }
    ],
    "cardSet": {
      "@id": "/card_sets/DUSTEROP",
      "@type": "CardSet",
      "id": "01K4YGEBN10S3MMN6J9CW5B4AC",
      "reference": "DUSTEROP",
      "name": "Seeds of Unity - Organized Play"
    },
    "rarity": {
      "@type": "Rarity",
      "@id": "/.well-known/genid/47c397db0d2b4bb3106a",
      "reference": "COMMON",
      "id": "01GE7AC9WEQKW1Y1BF8SCY745A",
      "name": "Common"
    },
    "imagePath": "https://altered-prod-eu.s3.amazonaws.com/Art/DUSTEROP/CARDS/ALT_DUSTEROP_A_LY_100/JPG/en_US/559bb7dd9c965e1c3f2d195d97cd9c7a.jpg",
    "assets": {
      "WEB": [
        "https://altered-prod-eu.s3.amazonaws.com/Art/DUSTEROP/CARDS/ALT_DUSTEROP_A_LY_100/WEB_bd0ea8beb3bd5e9543a5dcc0d57d3728",
        "https://altered-prod-eu.s3.amazonaws.com/Art/DUSTEROP/CARDS/ALT_DUSTEROP_A_LY_100/WEB_f262966630b2f39074ed083159b59e35"
      ]
    },
    "lowerPrice": 0,
    "qrUrlDetail": "https://qr.altered.gg/ALT_DUSTEROP_A_LY_100_C",
    "isOwnerless": false,
    "reference": "ALT_DUSTEROP_A_LY_100_C",
    "id": "01K4YGECGY9XSJBXPCXRG95JZ3",
    "mainFaction": {
      "@id": "/factions/LY",
      "@type": "Faction",
      "reference": "LY",
      "color": "#cf4171",
      "id": "01GE7AC9XGB6JE2V63WXWN4FB3",
      "name": "Lyra"
    },
    "allImagePath": {
      "fr-fr": "https://altered-prod-eu.s3.amazonaws.com/Art/DUSTEROP/CARDS/ALT_DUSTEROP_A_LY_100/JPG/fr_FR/2e52df9b7343c0f47e9306a497fbe597.jpg",
      "en-us": "https://altered-prod-eu.s3.amazonaws.com/Art/DUSTEROP/CARDS/ALT_DUSTEROP_A_LY_100/JPG/en_US/559bb7dd9c965e1c3f2d195d97cd9c7a.jpg",
      "it-it": "",
      "es-es": "",
      "de-de": ""
    },
    "name": "Romantic Encounter",
    "elements": {
      "MAIN_COST": "4",
      "RECALL_COST": "4",
      "MAIN_EFFECT": "Target opponent reveals the top four cards of their deck. You may play a Character from these cards for free and it gains [[Fleeting]], then discard the rest."
    },
    "isSuspended": false,
    "isErrated": false,
    "isBanned": false,
    "isSerialized": false,
    "isParentSerialized": false,
    "collectorNumber": "SDUOP-016-C-EN"
  },
  {
    "@context": "/contexts/Card",
    "@id": "/cards/ALT_DUSTEROP_A_LY_100_R1",
    "@type": "Card",
    "cardType": {
      "@id": "/card_types/01GE7AC9X35JXEQZJBBD6E4BKX",
      "@type": "CardType",
      "reference": "SPELL",
      "id": "01GE7AC9X35JXEQZJBBD6E4BKX",
      "name": "Spell"
    },
    "cardSubTypes": [
      {
        "@type": "CardSubType",
        "@id": "/.well-known/genid/e26ce3eefaf671317ec0",
        "reference": "MANEUVER",
        "id": "01HKAGPGT0M24AWMMF30CN0NT4",
        "name": "Maneuver"
      }
    ],
    "cardSet": {
      "@id": "/card_sets/DUSTEROP",
      "@type": "CardSet",
      "id": "01K4YGEBN10S3MMN6J9CW5B4AC",
      "reference": "DUSTEROP",
      "name": "Seeds of Unity - Organized Play"
    },
    "rarity": {
      "@type": "Rarity",
      "@id": "/.well-known/genid/1e7946c44158e3e9b6e3",
      "reference": "RARE",
      "id": "01GE7AC9WY6PK56RADXXD6P1T5",
      "name": "Rare"
    },
    "imagePath": "https://altered-prod-eu.s3.amazonaws.com/Art/DUSTEROP/CARDS/ALT_DUSTEROP_A_LY_100/JPG/en_US/b213df7024efc3cf8ab5b9e7dd08fbdb.jpg",
    "assets": {
      "WEB": [
        "https://altered-prod-eu.s3.amazonaws.com/Art/DUSTEROP/CARDS/ALT_DUSTEROP_A_LY_100/WEB_bd0ea8beb3bd5e9543a5dcc0d57d3728",
        "https://altered-prod-eu.s3.amazonaws.com/Art/DUSTEROP/CARDS/ALT_DUSTEROP_A_LY_100/WEB_f262966630b2f39074ed083159b59e35"
      ]
    },
    "lowerPrice": 0,
    "qrUrlDetail": "https://qr.altered.gg/ALT_DUSTEROP_A_LY_100_R1",
    "isOwnerless": false,
    "reference": "ALT_DUSTEROP_A_LY_100_R1",
    "id": "01K4YGECGY9XSJBXPCXRG95JZ6",
    "mainFaction": {
      "@id": "/factions/LY",
      "@type": "Faction",
      "reference": "LY",
      "color": "#cf4171",
      "id": "01GE7AC9XGB6JE2V63WXWN4FB3",
      "name": "Lyra"
    },
    "allImagePath": {
      "fr-fr": "https://altered-prod-eu.s3.amazonaws.com/Art/DUSTEROP/CARDS/ALT_DUSTEROP_A_LY_100/JPG/fr_FR/0f30b3967460129a7bf4a8676201f25f.jpg",
      "en-us": "https://altered-prod-eu.s3.amazonaws.com/Art/DUSTEROP/CARDS/ALT_DUSTEROP_A_LY_100/JPG/en_US/b213df7024efc3cf8ab5b9e7dd08fbdb.jpg",
      "it-it": "",
      "es-es": "",
      "de-de": ""
    },
    "name": "Romantic Encounter",
    "elements": {
      "MAIN_COST": "#7#",
      "RECALL_COST": "#7#",
      "MAIN_EFFECT": "#[[Fleeting]].#  #Do this for each player, starting with you:#  • That player reveals the top four cards of their deck. You may play a Character #with Base Cost {3} or less# from these cards for free and it gains [[Fleeting]], then discard the rest."
    },
    "isSuspended": false,
    "isErrated": false,
    "isBanned": false,
    "isSerialized": false,
    "isParentSerialized": false,
    "collectorNumber": "SDUOP-016-R-EN"
  },
  {
    "@context": "/contexts/Card",
    "@id": "/cards/ALT_DUSTEROP_A_MU_98_R2",
    "@type": "Card",
    "cardType": {
      "@id": "/card_types/01GE7AC9X35JXEQZJBBD6E4BKX",
      "@type": "CardType",
      "reference": "SPELL",
      "id": "01GE7AC9X35JXEQZJBBD6E4BKX",
      "name": "Spell"
    },
    "cardSubTypes": [
      {
        "@type": "CardSubType",
        "@id": "/.well-known/genid/97a0fba49008bc7a4ff9",
        "reference": "BOON",
        "id": "01HKAGPHVVK20XKBXKCZNGRTFD",
        "name": "Boon"
      },
      {
        "@type": "CardSubType",
        "@id": "/.well-known/genid/77e106d2553a4e2a8a2b",
        "reference": "MANEUVER",
        "id": "01HKAGPGT0M24AWMMF30CN0NT4",
        "name": "Maneuver"
      }
    ],
    "cardSet": {
      "@id": "/card_sets/DUSTEROP",
      "@type": "CardSet",
      "id": "01K4YGEBN10S3MMN6J9CW5B4AC",
      "reference": "DUSTEROP",
      "name": "Seeds of Unity - Organized Play"
    },
    "rarity": {
      "@type": "Rarity",
      "@id": "/.well-known/genid/2137c22e5a0fe0062d2c",
      "reference": "RARE",
      "id": "01GE7AC9WY6PK56RADXXD6P1T5",
      "name": "Rare"
    },
    "imagePath": "https://altered-prod-eu.s3.amazonaws.com/Art/DUSTEROP/CARDS/ALT_DUSTEROP_A_MU_98/JPG/en_US/43ac5fe2e15c658ed55ac7307f24080d.jpg",
    "assets": {
      "WEB": [
        "https://altered-prod-eu.s3.amazonaws.com/Art/DUSTEROP/CARDS/ALT_DUSTEROP_A_MU_98/WEB_88deb0b8dbb774637986dfd99042de98",
        "https://altered-prod-eu.s3.amazonaws.com/Art/DUSTEROP/CARDS/ALT_DUSTEROP_A_MU_98/WEB_eeacf8ec4015ecda3528b920398f8506"
      ]
    },
    "lowerPrice": 0,
    "qrUrlDetail": "https://qr.altered.gg/ALT_DUSTEROP_A_MU_98_R2",
    "isOwnerless": false,
    "reference": "ALT_DUSTEROP_A_MU_98_R2",
    "id": "01K4YGECH13XFX6RFD000JVSWD",
    "mainFaction": {
      "@id": "/factions/LY",
      "@type": "Faction",
      "reference": "LY",
      "color": "#cf4171",
      "id": "01GE7AC9XGB6JE2V63WXWN4FB3",
      "name": "Lyra"
    },
    "allImagePath": {
      "fr-fr": "https://altered-prod-eu.s3.amazonaws.com/Art/DUSTEROP/CARDS/ALT_DUSTEROP_A_MU_98/JPG/fr_FR/36657fbd43767be370ce31f006ff5ec3.jpg",
      "en-us": "https://altered-prod-eu.s3.amazonaws.com/Art/DUSTEROP/CARDS/ALT_DUSTEROP_A_MU_98/JPG/en_US/43ac5fe2e15c658ed55ac7307f24080d.jpg",
      "it-it": "",
      "es-es": "",
      "de-de": ""
    },
    "name": "Soul Encounter",
    "elements": {
      "MAIN_COST": "3",
      "RECALL_COST": "#2#",
      "MAIN_EFFECT": "#[Cooldown].#  Distribute 4 boosts among any target Characters in play or in Reserve."
    },
    "isSuspended": false,
    "isErrated": false,
    "isBanned": false,
    "isSerialized": false,
    "isParentSerialized": false,
    "collectorNumber": "SDUOP-017-F-EN"
  },
  {
    "@context": "/contexts/Card",
    "@id": "/cards/ALT_DUSTEROP_A_OR_98_R2",
    "@type": "Card",
    "cardType": {
      "@id": "/card_types/01GE7AC9X35JXEQZJBBD6E4BKX",
      "@type": "CardType",
      "reference": "SPELL",
      "id": "01GE7AC9X35JXEQZJBBD6E4BKX",
      "name": "Spell"
    },
    "cardSubTypes": [
      {
        "@type": "CardSubType",
        "@id": "/.well-known/genid/2912f166423be7a5841c",
        "reference": "DISRUPTION",
        "id": "01HKAGPH80FC347E2P8841D298",
        "name": "Disruption"
      },
      {
        "@type": "CardSubType",
        "@id": "/.well-known/genid/27688143d722bd2ad06d",
        "reference": "MANEUVER",
        "id": "01HKAGPGT0M24AWMMF30CN0NT4",
        "name": "Maneuver"
      }
    ],
    "cardSet": {
      "@id": "/card_sets/DUSTEROP",
      "@type": "CardSet",
      "id": "01K4YGEBN10S3MMN6J9CW5B4AC",
      "reference": "DUSTEROP",
      "name": "Seeds of Unity - Organized Play"
    },
    "rarity": {
      "@type": "Rarity",
      "@id": "/.well-known/genid/a3eae3e693643f5143c1",
      "reference": "RARE",
      "id": "01GE7AC9WY6PK56RADXXD6P1T5",
      "name": "Rare"
    },
    "imagePath": "https://altered-prod-eu.s3.amazonaws.com/Art/DUSTEROP/CARDS/ALT_DUSTEROP_A_OR_98/JPG/en_US/637c61241d270f8f0a755e8c6ba3ac94.jpg",
    "assets": {
      "WEB": [
        "https://altered-prod-eu.s3.amazonaws.com/Art/DUSTEROP/CARDS/ALT_DUSTEROP_A_OR_98/WEB_52cf1121a153eb736f575299ebb7a427",
        "https://altered-prod-eu.s3.amazonaws.com/Art/DUSTEROP/CARDS/ALT_DUSTEROP_A_OR_98/WEB_df1a426454c8edc774fd2d2021175a63"
      ]
    },
    "lowerPrice": 0,
    "qrUrlDetail": "https://qr.altered.gg/ALT_DUSTEROP_A_OR_98_R2",
    "isOwnerless": false,
    "reference": "ALT_DUSTEROP_A_OR_98_R2",
    "id": "01K4YGECH5B52PVNSD8WASC8VP",
    "mainFaction": {
      "@id": "/factions/LY",
      "@type": "Faction",
      "reference": "LY",
      "color": "#cf4171",
      "id": "01GE7AC9XGB6JE2V63WXWN4FB3",
      "name": "Lyra"
    },
    "allImagePath": {
      "fr-fr": "https://altered-prod-eu.s3.amazonaws.com/Art/DUSTEROP/CARDS/ALT_DUSTEROP_A_OR_98/JPG/fr_FR/75e40cd79bd672beee196f083b683ea8.jpg",
      "en-us": "https://altered-prod-eu.s3.amazonaws.com/Art/DUSTEROP/CARDS/ALT_DUSTEROP_A_OR_98/JPG/en_US/637c61241d270f8f0a755e8c6ba3ac94.jpg",
      "it-it": "",
      "es-es": "",
      "de-de": ""
    },
    "name": "Unfair Encounter",
    "elements": {
      "MAIN_COST": "#3#",
      "RECALL_COST": "#3#",
      "MAIN_EFFECT": "[[Fleeting]].  Target a Landmark Permanent with Hand Cost {2} or less. #Its controller [Resupplies],# then you take control of it."
    },
    "isSuspended": false,
    "isErrated": false,
    "isBanned": false,
    "isSerialized": false,
    "isParentSerialized": false,
    "collectorNumber": "SDUOP-018-F-EN"
  },
  {
    "@context": "/contexts/Card",
    "@id": "/cards/ALT_DUSTEROP_P_MU_94_C",
    "@type": "Card",
    "cardType": {
      "@id": "/card_types/01H19NWA92A4ERAC4ATMSZNASS",
      "@type": "CardType",
      "reference": "CHARACTER",
      "id": "01H19NWA92A4ERAC4ATMSZNASS",
      "name": "Character"
    },
    "cardSubTypes": [
      {
        "@type": "CardSubType",
        "@id": "/.well-known/genid/c0cebd7eda1d7ce0ed65",
        "reference": "CITIZEN",
        "id": "01HKAGQWDFDGS8YVZGW98BVV9D",
        "name": "Citizen"
      }
    ],
    "cardSet": {
      "@id": "/card_sets/DUSTEROP",
      "@type": "CardSet",
      "id": "01K4YGEBN10S3MMN6J9CW5B4AC",
      "reference": "DUSTEROP",
      "name": "Seeds of Unity - Organized Play"
    },
    "rarity": {
      "@type": "Rarity",
      "@id": "/.well-known/genid/b3040075d93dbe86a62d",
      "reference": "COMMON",
      "id": "01GE7AC9WEQKW1Y1BF8SCY745A",
      "name": "Common"
    },
    "imagePath": "https://altered-prod-eu.s3.amazonaws.com/Art/DUSTEROP/CARDS/ALT_DUSTEROP_P_MU_94/JPG/en_US/5850e5bf1869941dbe6de9640567f7db.jpg",
    "assets": {
      "WEB": [
        "https://altered-prod-eu.s3.amazonaws.com/Art/DUSTEROP/CARDS/ALT_DUSTEROP_P_MU_94/WEB_24b6c4e79abf6998245bc88e02d67e22",
        "https://altered-prod-eu.s3.amazonaws.com/Art/DUSTEROP/CARDS/ALT_DUSTEROP_P_MU_94/WEB_f8500d222be543c2d33e45bfbd6428ec",
        "https://altered-prod-eu.s3.amazonaws.com/Art/DUSTEROP/CARDS/ALT_DUSTEROP_P_MU_94/WEB_eebc7faf83fccc57e95f804b47ebbf3a"
      ]
    },
    "lowerPrice": 0,
    "qrUrlDetail": "https://qr.altered.gg/ALT_DUSTEROP_P_MU_94_C",
    "isOwnerless": false,
    "reference": "ALT_DUSTEROP_P_MU_94_C",
    "id": "01K4YGECH04GAPYFPJ439PFD7J",
    "mainFaction": {
      "@id": "/factions/MU",
      "@type": "Faction",
      "reference": "MU",
      "color": "#3d6b42",
      "id": "01GE7AC9X2BNM40TTAYAEFSZSJ",
      "name": "Muna"
    },
    "allImagePath": {
      "fr-fr": "https://altered-prod-eu.s3.amazonaws.com/Art/DUSTEROP/CARDS/ALT_DUSTEROP_P_MU_94/JPG/fr_FR/e995d22ac9dbd56c74741ef837e1a778.jpg",
      "en-us": "https://altered-prod-eu.s3.amazonaws.com/Art/DUSTEROP/CARDS/ALT_DUSTEROP_P_MU_94/JPG/en_US/5850e5bf1869941dbe6de9640567f7db.jpg",
      "it-it": "",
      "es-es": "",
      "de-de": ""
    },
    "name": "Reka Gatherer",
    "elements": {
      "MAIN_COST": "2",
      "RECALL_COST": "2",
      "OCEAN_POWER": "2",
      "FOREST_POWER": "2",
      "MOUNTAIN_POWER": "2",
      "ECHO_EFFECT": "{D} : Create a [Manaseed] token in each player's Landmarks."
    },
    "isSuspended": false,
    "isErrated": false,
    "isBanned": false,
    "isSerialized": false,
    "isParentSerialized": false,
    "collectorNumber": "SDUOP-004-C-EN"
  },
  {
    "@context": "/contexts/Card",
    "@id": "/cards/ALT_DUSTEROP_P_MU_89_R1",
    "@type": "Card",
    "cardType": {
      "@id": "/card_types/01H19NWA92A4ERAC4ATMSZNASS",
      "@type": "CardType",
      "reference": "CHARACTER",
      "id": "01H19NWA92A4ERAC4ATMSZNASS",
      "name": "Character"
    },
    "cardSubTypes": [
      {
        "@type": "CardSubType",
        "@id": "/.well-known/genid/1a05f00c05b7c9f8a004",
        "reference": "CITIZEN",
        "id": "01HKAGQWDFDGS8YVZGW98BVV9D",
        "name": "Citizen"
      }
    ],
    "cardSet": {
      "@id": "/card_sets/DUSTEROP",
      "@type": "CardSet",
      "id": "01K4YGEBN10S3MMN6J9CW5B4AC",
      "reference": "DUSTEROP",
      "name": "Seeds of Unity - Organized Play"
    },
    "rarity": {
      "@type": "Rarity",
      "@id": "/.well-known/genid/3a413d63d27ef443337b",
      "reference": "RARE",
      "id": "01GE7AC9WY6PK56RADXXD6P1T5",
      "name": "Rare"
    },
    "imagePath": "https://altered-prod-eu.s3.amazonaws.com/Art/DUSTEROP/CARDS/ALT_DUSTEROP_P_MU_89/JPG/en_US/14e9a2b06ab368bf062ed012fcf21b25.jpg",
    "assets": {
      "WEB": [
        "https://altered-prod-eu.s3.amazonaws.com/Art/DUSTEROP/CARDS/ALT_DUSTEROP_P_MU_89/WEB_0b0f405d331a720240420950455dc2c8",
        "https://altered-prod-eu.s3.amazonaws.com/Art/DUSTEROP/CARDS/ALT_DUSTEROP_P_MU_89/WEB_17dcb69af0ff5383fa17905c6a171a36",
        "https://altered-prod-eu.s3.amazonaws.com/Art/DUSTEROP/CARDS/ALT_DUSTEROP_P_MU_89/WEB_3d59fad97aa8a13800e965373e5f3d0b"
      ]
    },
    "lowerPrice": 0,
    "qrUrlDetail": "https://qr.altered.gg/ALT_DUSTEROP_P_MU_89_R1",
    "isOwnerless": false,
    "reference": "ALT_DUSTEROP_P_MU_89_R1",
    "id": "01K4YGECH13XFX6RFD000JVSW1",
    "mainFaction": {
      "@id": "/factions/MU",
      "@type": "Faction",
      "reference": "MU",
      "color": "#3d6b42",
      "id": "01GE7AC9X2BNM40TTAYAEFSZSJ",
      "name": "Muna"
    },
    "allImagePath": {
      "fr-fr": "https://altered-prod-eu.s3.amazonaws.com/Art/DUSTEROP/CARDS/ALT_DUSTEROP_P_MU_89/JPG/fr_FR/cdcf51b808dba33750545a8cc8b4ee21.jpg",
      "en-us": "https://altered-prod-eu.s3.amazonaws.com/Art/DUSTEROP/CARDS/ALT_DUSTEROP_P_MU_89/JPG/en_US/14e9a2b06ab368bf062ed012fcf21b25.jpg",
      "it-it": "",
      "es-es": "",
      "de-de": ""
    },
    "name": "Charitable Reka",
    "elements": {
      "MAIN_COST": "2",
      "RECALL_COST": "2",
      "OCEAN_POWER": "3",
      "FOREST_POWER": "3",
      "MOUNTAIN_POWER": "0",
      "MAIN_EFFECT": "#{J} Create a [Manaseed] token in each player's Landmarks.#"
    },
    "isSuspended": false,
    "isErrated": false,
    "isBanned": false,
    "isSerialized": false,
    "isParentSerialized": false,
    "collectorNumber": "SDUOP-010-R-EN"
  },
  {
    "@context": "/contexts/Card",
    "@id": "/cards/ALT_DUSTEROP_A_MU_98_C",
    "@type": "Card",
    "cardType": {
      "@id": "/card_types/01GE7AC9X35JXEQZJBBD6E4BKX",
      "@type": "CardType",
      "reference": "SPELL",
      "id": "01GE7AC9X35JXEQZJBBD6E4BKX",
      "name": "Spell"
    },
    "cardSubTypes": [
      {
        "@type": "CardSubType",
        "@id": "/.well-known/genid/6aa1c88f2d05e7b6347d",
        "reference": "BOON",
        "id": "01HKAGPHVVK20XKBXKCZNGRTFD",
        "name": "Boon"
      },
      {
        "@type": "CardSubType",
        "@id": "/.well-known/genid/212af327ee8d1b395a8b",
        "reference": "MANEUVER",
        "id": "01HKAGPGT0M24AWMMF30CN0NT4",
        "name": "Maneuver"
      }
    ],
    "cardSet": {
      "@id": "/card_sets/DUSTEROP",
      "@type": "CardSet",
      "id": "01K4YGEBN10S3MMN6J9CW5B4AC",
      "reference": "DUSTEROP",
      "name": "Seeds of Unity - Organized Play"
    },
    "rarity": {
      "@type": "Rarity",
      "@id": "/.well-known/genid/a200599895a025f8718e",
      "reference": "COMMON",
      "id": "01GE7AC9WEQKW1Y1BF8SCY745A",
      "name": "Common"
    },
    "imagePath": "https://altered-prod-eu.s3.amazonaws.com/Art/DUSTEROP/CARDS/ALT_DUSTEROP_A_MU_98/JPG/en_US/e5c8f77982654e4bc89e261195513cfb.jpg",
    "assets": {
      "WEB": [
        "https://altered-prod-eu.s3.amazonaws.com/Art/DUSTEROP/CARDS/ALT_DUSTEROP_A_MU_98/WEB_88deb0b8dbb774637986dfd99042de98",
        "https://altered-prod-eu.s3.amazonaws.com/Art/DUSTEROP/CARDS/ALT_DUSTEROP_A_MU_98/WEB_eeacf8ec4015ecda3528b920398f8506"
      ]
    },
    "lowerPrice": 0,
    "qrUrlDetail": "https://qr.altered.gg/ALT_DUSTEROP_A_MU_98_C",
    "isOwnerless": false,
    "reference": "ALT_DUSTEROP_A_MU_98_C",
    "id": "01K4YGECH13XFX6RFD000JVSW7",
    "mainFaction": {
      "@id": "/factions/MU",
      "@type": "Faction",
      "reference": "MU",
      "color": "#3d6b42",
      "id": "01GE7AC9X2BNM40TTAYAEFSZSJ",
      "name": "Muna"
    },
    "allImagePath": {
      "fr-fr": "https://altered-prod-eu.s3.amazonaws.com/Art/DUSTEROP/CARDS/ALT_DUSTEROP_A_MU_98/JPG/fr_FR/089e35624713e801f517ab7462a942fb.jpg",
      "en-us": "https://altered-prod-eu.s3.amazonaws.com/Art/DUSTEROP/CARDS/ALT_DUSTEROP_A_MU_98/JPG/en_US/e5c8f77982654e4bc89e261195513cfb.jpg",
      "it-it": "",
      "es-es": "",
      "de-de": ""
    },
    "name": "Soul Encounter",
    "elements": {
      "MAIN_COST": "3",
      "RECALL_COST": "3",
      "MAIN_EFFECT": "Distribute 4 boosts among any target Characters in play or in Reserve."
    },
    "isSuspended": false,
    "isErrated": false,
    "isBanned": false,
    "isSerialized": false,
    "isParentSerialized": false,
    "collectorNumber": "SDUOP-017-C-EN"
  },
  {
    "@context": "/contexts/Card",
    "@id": "/cards/ALT_DUSTEROP_A_MU_98_R1",
    "@type": "Card",
    "cardType": {
      "@id": "/card_types/01GE7AC9X35JXEQZJBBD6E4BKX",
      "@type": "CardType",
      "reference": "SPELL",
      "id": "01GE7AC9X35JXEQZJBBD6E4BKX",
      "name": "Spell"
    },
    "cardSubTypes": [
      {
        "@type": "CardSubType",
        "@id": "/.well-known/genid/01ad9310e50c63ff33a3",
        "reference": "BOON",
        "id": "01HKAGPHVVK20XKBXKCZNGRTFD",
        "name": "Boon"
      },
      {
        "@type": "CardSubType",
        "@id": "/.well-known/genid/8c044b649a817209ccd4",
        "reference": "MANEUVER",
        "id": "01HKAGPGT0M24AWMMF30CN0NT4",
        "name": "Maneuver"
      }
    ],
    "cardSet": {
      "@id": "/card_sets/DUSTEROP",
      "@type": "CardSet",
      "id": "01K4YGEBN10S3MMN6J9CW5B4AC",
      "reference": "DUSTEROP",
      "name": "Seeds of Unity - Organized Play"
    },
    "rarity": {
      "@type": "Rarity",
      "@id": "/.well-known/genid/fd61ab4b2eae5b68f187",
      "reference": "RARE",
      "id": "01GE7AC9WY6PK56RADXXD6P1T5",
      "name": "Rare"
    },
    "imagePath": "https://altered-prod-eu.s3.amazonaws.com/Art/DUSTEROP/CARDS/ALT_DUSTEROP_A_MU_98/JPG/en_US/270095b36a08d4b17468d4463c0353b3.jpg",
    "assets": {
      "WEB": [
        "https://altered-prod-eu.s3.amazonaws.com/Art/DUSTEROP/CARDS/ALT_DUSTEROP_A_MU_98/WEB_88deb0b8dbb774637986dfd99042de98",
        "https://altered-prod-eu.s3.amazonaws.com/Art/DUSTEROP/CARDS/ALT_DUSTEROP_A_MU_98/WEB_eeacf8ec4015ecda3528b920398f8506"
      ]
    },
    "lowerPrice": 0,
    "qrUrlDetail": "https://qr.altered.gg/ALT_DUSTEROP_A_MU_98_R1",
    "isOwnerless": false,
    "reference": "ALT_DUSTEROP_A_MU_98_R1",
    "id": "01K4YGECH13XFX6RFD000JVSWA",
    "mainFaction": {
      "@id": "/factions/MU",
      "@type": "Faction",
      "reference": "MU",
      "color": "#3d6b42",
      "id": "01GE7AC9X2BNM40TTAYAEFSZSJ",
      "name": "Muna"
    },
    "allImagePath": {
      "fr-fr": "https://altered-prod-eu.s3.amazonaws.com/Art/DUSTEROP/CARDS/ALT_DUSTEROP_A_MU_98/JPG/fr_FR/abfb38bd6ed151acbb84704aa7538555.jpg",
      "en-us": "https://altered-prod-eu.s3.amazonaws.com/Art/DUSTEROP/CARDS/ALT_DUSTEROP_A_MU_98/JPG/en_US/270095b36a08d4b17468d4463c0353b3.jpg",
      "it-it": "",
      "es-es": "",
      "de-de": ""
    },
    "name": "Soul Encounter",
    "elements": {
      "MAIN_COST": "3",
      "RECALL_COST": "#2#",
      "MAIN_EFFECT": "#[Cooldown].#  Distribute 4 boosts among any target Characters in play or in Reserve."
    },
    "isSuspended": false,
    "isErrated": false,
    "isBanned": false,
    "isSerialized": false,
    "isParentSerialized": false,
    "collectorNumber": "SDUOP-017-R-EN"
  },
  {
    "@context": "/contexts/Card",
    "@id": "/cards/ALT_DUSTEROP_A_MU_83_C",
    "@type": "Card",
    "cardType": {
      "@id": "/card_types/01H0FV1VGP26CD3DFE8W3PWTQT",
      "@type": "CardType",
      "reference": "TOKEN",
      "id": "01H0FV1VGP26CD3DFE8W3PWTQT",
      "name": "Token Character"
    },
    "cardSubTypes": [
      {
        "@type": "CardSubType",
        "@id": "/.well-known/genid/7050c3882c66c7fb50b6",
        "reference": "ANIMAL",
        "id": "01HKAGQS36Z3DP166MZW8KRAEK",
        "name": "Animal"
      }
    ],
    "cardSet": {
      "@id": "/card_sets/DUSTEROP",
      "@type": "CardSet",
      "id": "01K4YGEBN10S3MMN6J9CW5B4AC",
      "reference": "DUSTEROP",
      "name": "Seeds of Unity - Organized Play"
    },
    "rarity": {
      "@type": "Rarity",
      "@id": "/.well-known/genid/aca0448f1cb4adfb3b92",
      "reference": "COMMON",
      "id": "01GE7AC9WEQKW1Y1BF8SCY745A",
      "name": "Common"
    },
    "imagePath": "https://altered-prod-eu.s3.amazonaws.com/Art/DUSTEROP/CARDS/ALT_DUSTEROP_A_MU_83/JPG/en_US/245960274810f6bbb44160dd95493255.jpg",
    "assets": {
      "WEB": [
        "https://altered-prod-eu.s3.amazonaws.com/Art/DUSTEROP/CARDS/ALT_DUSTEROP_A_MU_83/WEB_62fe90c74bf107362dff307e6e450e8f"
      ]
    },
    "lowerPrice": 0,
    "qrUrlDetail": "https://qr.altered.gg/ALT_DUSTEROP_A_MU_83_C",
    "isOwnerless": false,
    "reference": "ALT_DUSTEROP_A_MU_83_C",
    "id": "01KECGKEFQDSP605BFFGNKNT00",
    "mainFaction": {
      "@id": "/factions/MU",
      "@type": "Faction",
      "reference": "MU",
      "color": "#3d6b42",
      "id": "01GE7AC9X2BNM40TTAYAEFSZSJ",
      "name": "Muna"
    },
    "allImagePath": {
      "fr-fr": "https://altered-prod-eu.s3.amazonaws.com/Art/DUSTEROP/CARDS/ALT_DUSTEROP_A_MU_83/JPG/fr_FR/103c5fdf59714cdb3ff6de6922b835b5.jpg",
      "en-us": "https://altered-prod-eu.s3.amazonaws.com/Art/DUSTEROP/CARDS/ALT_DUSTEROP_A_MU_83/JPG/en_US/245960274810f6bbb44160dd95493255.jpg",
      "it-it": "https://altered-prod-eu.s3.amazonaws.com/Art/DUSTEROP/CARDS/ALT_DUSTEROP_A_MU_83/JPG/it_IT/1eec4707d8d41624fefd325ed7e7fb5c.jpg",
      "es-es": "https://altered-prod-eu.s3.amazonaws.com/Art/DUSTEROP/CARDS/ALT_DUSTEROP_A_MU_83/JPG/es_ES/61d8f608b9591d5931f1a8d23e54ef54.jpg",
      "de-de": "https://altered-prod-eu.s3.amazonaws.com/Art/DUSTEROP/CARDS/ALT_DUSTEROP_A_MU_83/JPG/de_DE/60a5ad9d8f39e9a82a5b2edfdf22d1ec.jpg"
    },
    "name": "Woollyback",
    "elements": {
      "MAIN_COST": "0",
      "RECALL_COST": "0",
      "OCEAN_POWER": "1",
      "MOUNTAIN_POWER": "1",
      "FOREST_POWER": "1"
    },
    "isSuspended": false,
    "isErrated": false,
    "isBanned": false,
    "isSerialized": false,
    "isParentSerialized": false,
    "collectorNumber": "SDUOP-023-T-EN"
  },
  {
    "@context": "/contexts/Card",
    "@id": "/cards/ALT_DUSTEROP_P_OR_100_C",
    "@type": "Card",
    "cardType": {
      "@id": "/card_types/01J1Q78N4S1E64PN4T7GB4T59F",
      "@type": "CardType",
      "reference": "LANDMARK_PERMANENT",
      "id": "01J1Q78N4S1E64PN4T7GB4T59F",
      "name": "Landmark Permanent"
    },
    "cardSubTypes": [
      {
        "@type": "CardSubType",
        "@id": "/.well-known/genid/798ab95d917e3368e63a",
        "reference": "SITE",
        "id": "01J1SYC3P1C9H7CT2H8C0WN9CT",
        "name": "Site"
      }
    ],
    "cardSet": {
      "@id": "/card_sets/DUSTEROP",
      "@type": "CardSet",
      "id": "01K4YGEBN10S3MMN6J9CW5B4AC",
      "reference": "DUSTEROP",
      "name": "Seeds of Unity - Organized Play"
    },
    "rarity": {
      "@type": "Rarity",
      "@id": "/.well-known/genid/8d21c050629cce079400",
      "reference": "COMMON",
      "id": "01GE7AC9WEQKW1Y1BF8SCY745A",
      "name": "Common"
    },
    "imagePath": "https://altered-prod-eu.s3.amazonaws.com/Art/DUSTEROP/CARDS/ALT_DUSTEROP_P_OR_100/JPG/en_US/39a83c8f69cdcaa2faaeb04cb07ea1ee.jpg",
    "assets": {
      "WEB": [
        "https://altered-prod-eu.s3.amazonaws.com/Art/DUSTEROP/CARDS/ALT_DUSTEROP_P_OR_100/WEB_6134035e5c60056c07fea03a3e6459ea",
        "https://altered-prod-eu.s3.amazonaws.com/Art/DUSTEROP/CARDS/ALT_DUSTEROP_P_OR_100/WEB_adca83d0a850b935e69697eed85c608c"
      ]
    },
    "lowerPrice": 0,
    "qrUrlDetail": "https://qr.altered.gg/ALT_DUSTEROP_P_OR_100_C",
    "isOwnerless": false,
    "reference": "ALT_DUSTEROP_P_OR_100_C",
    "id": "01K4YGECH3JKGXH6R3FGTF53H8",
    "mainFaction": {
      "@id": "/factions/OR",
      "@type": "Faction",
      "reference": "OR",
      "color": "#0f6593",
      "id": "01GE7AC9X78DXSNKNB15KCF69X",
      "name": "Ordis"
    },
    "allImagePath": {
      "fr-fr": "https://altered-prod-eu.s3.amazonaws.com/Art/DUSTEROP/CARDS/ALT_DUSTEROP_P_OR_100/JPG/fr_FR/359c34e33d0bab42eb0b30e629c748e0.jpg",
      "en-us": "https://altered-prod-eu.s3.amazonaws.com/Art/DUSTEROP/CARDS/ALT_DUSTEROP_P_OR_100/JPG/en_US/39a83c8f69cdcaa2faaeb04cb07ea1ee.jpg",
      "it-it": "",
      "es-es": "",
      "de-de": ""
    },
    "name": "The Lectern",
    "elements": {
      "MAIN_COST": "2",
      "RECALL_COST": "2",
      "MAIN_EFFECT": "{J} [Resupply].  When I'm sacrificed — Create an [Ordis Recruit 1/1/1] in a Hero Expedition."
    },
    "isSuspended": false,
    "isErrated": false,
    "isBanned": false,
    "isSerialized": false,
    "isParentSerialized": false,
    "collectorNumber": "SDUOP-005-C-EN"
  },
  {
    "@context": "/contexts/Card",
    "@id": "/cards/ALT_DUSTEROP_P_OR_86_R1",
    "@type": "Card",
    "cardType": {
      "@id": "/card_types/01H19NWA92A4ERAC4ATMSZNASS",
      "@type": "CardType",
      "reference": "CHARACTER",
      "id": "01H19NWA92A4ERAC4ATMSZNASS",
      "name": "Character"
    },
    "cardSubTypes": [
      {
        "@type": "CardSubType",
        "@id": "/.well-known/genid/b5df613d5906b9564717",
        "reference": "ENGINEER",
        "id": "01HKAGPA9AS71JN0H9HQZTBNCD",
        "name": "Engineer"
      }
    ],
    "cardSet": {
      "@id": "/card_sets/DUSTEROP",
      "@type": "CardSet",
      "id": "01K4YGEBN10S3MMN6J9CW5B4AC",
      "reference": "DUSTEROP",
      "name": "Seeds of Unity - Organized Play"
    },
    "rarity": {
      "@type": "Rarity",
      "@id": "/.well-known/genid/981b282a1fe826a680cf",
      "reference": "RARE",
      "id": "01GE7AC9WY6PK56RADXXD6P1T5",
      "name": "Rare"
    },
    "imagePath": "https://altered-prod-eu.s3.amazonaws.com/Art/DUSTEROP/CARDS/ALT_DUSTEROP_P_OR_86/JPG/en_US/2140eed250a46842ca0df19e86940960.jpg",
    "assets": {
      "WEB": [
        "https://altered-prod-eu.s3.amazonaws.com/Art/DUSTEROP/CARDS/ALT_DUSTEROP_P_OR_86/WEB_1c348955b50468bcec2bedaa3344357a",
        "https://altered-prod-eu.s3.amazonaws.com/Art/DUSTEROP/CARDS/ALT_DUSTEROP_P_OR_86/WEB_7bfe5fac3ae0b4c54e58ba1fe82b7fe0",
        "https://altered-prod-eu.s3.amazonaws.com/Art/DUSTEROP/CARDS/ALT_DUSTEROP_P_OR_86/WEB_33e1c3a5dfe0a879515e94ac8b34107a"
      ]
    },
    "lowerPrice": 0,
    "qrUrlDetail": "https://qr.altered.gg/ALT_DUSTEROP_P_OR_86_R1",
    "isOwnerless": false,
    "reference": "ALT_DUSTEROP_P_OR_86_R1",
    "id": "01K4YGECH4RMXXTM87KCSRYQ1F",
    "mainFaction": {
      "@id": "/factions/OR",
      "@type": "Faction",
      "reference": "OR",
      "color": "#0f6593",
      "id": "01GE7AC9X78DXSNKNB15KCF69X",
      "name": "Ordis"
    },
    "allImagePath": {
      "fr-fr": "https://altered-prod-eu.s3.amazonaws.com/Art/DUSTEROP/CARDS/ALT_DUSTEROP_P_OR_86/JPG/fr_FR/d8a5cb3af0c980fb6f6088c121e775c7.jpg",
      "en-us": "https://altered-prod-eu.s3.amazonaws.com/Art/DUSTEROP/CARDS/ALT_DUSTEROP_P_OR_86/JPG/en_US/2140eed250a46842ca0df19e86940960.jpg",
      "it-it": "",
      "es-es": "",
      "de-de": ""
    },
    "name": "Louis Sullivan",
    "elements": {
      "MAIN_COST": "3",
      "RECALL_COST": "3",
      "OCEAN_POWER": "2",
      "FOREST_POWER": "#2#",
      "MOUNTAIN_POWER": "3",
      "MAIN_EFFECT": "#{J}# If there are #three or more# cards in your Landmarks, draw a card."
    },
    "isSuspended": false,
    "isErrated": false,
    "isBanned": false,
    "isSerialized": false,
    "isParentSerialized": false,
    "collectorNumber": "SDUOP-011-R-EN"
  },
  {
    "@context": "/contexts/Card",
    "@id": "/cards/ALT_DUSTEROP_P_OR_101_C",
    "@type": "Card",
    "cardType": {
      "@id": "/card_types/01J1Q78N4S1E64PN4T7GB4T59F",
      "@type": "CardType",
      "reference": "LANDMARK_PERMANENT",
      "id": "01J1Q78N4S1E64PN4T7GB4T59F",
      "name": "Landmark Permanent"
    },
    "cardSubTypes": [
      {
        "@type": "CardSubType",
        "@id": "/.well-known/genid/bf9fc5555f6e46d6cf94",
        "reference": "CONSTRUCTION",
        "id": "01J1SYC159ACKJS202498RAQRR",
        "name": "Construction"
      }
    ],
    "cardSet": {
      "@id": "/card_sets/DUSTEROP",
      "@type": "CardSet",
      "id": "01K4YGEBN10S3MMN6J9CW5B4AC",
      "reference": "DUSTEROP",
      "name": "Seeds of Unity - Organized Play"
    },
    "rarity": {
      "@type": "Rarity",
      "@id": "/.well-known/genid/204bedd9887416d1e1f3",
      "reference": "COMMON",
      "id": "01GE7AC9WEQKW1Y1BF8SCY745A",
      "name": "Common"
    },
    "imagePath": "https://altered-prod-eu.s3.amazonaws.com/Art/DUSTEROP/CARDS/ALT_DUSTEROP_P_OR_101/JPG/en_US/507bc8dbcad4c6e0e952712ea55eb43a.jpg",
    "assets": {
      "WEB": [
        "https://altered-prod-eu.s3.amazonaws.com/Art/DUSTEROP/CARDS/ALT_DUSTEROP_P_OR_101/WEB_c5a1c01e8701bc81c04899bbbbf04ba7",
        "https://altered-prod-eu.s3.amazonaws.com/Art/DUSTEROP/CARDS/ALT_DUSTEROP_P_OR_101/WEB_5e52178818bbde434cbbb4977e378013"
      ]
    },
    "lowerPrice": 0,
    "qrUrlDetail": "https://qr.altered.gg/ALT_DUSTEROP_P_OR_101_C",
    "isOwnerless": false,
    "reference": "ALT_DUSTEROP_P_OR_101_C",
    "id": "01K4YGECH4RMXXTM87KCSRYQ1N",
    "mainFaction": {
      "@id": "/factions/OR",
      "@type": "Faction",
      "reference": "OR",
      "color": "#0f6593",
      "id": "01GE7AC9X78DXSNKNB15KCF69X",
      "name": "Ordis"
    },
    "allImagePath": {
      "fr-fr": "https://altered-prod-eu.s3.amazonaws.com/Art/DUSTEROP/CARDS/ALT_DUSTEROP_P_OR_101/JPG/fr_FR/f1c3d829ac09426f82528afb5a42844e.jpg",
      "en-us": "https://altered-prod-eu.s3.amazonaws.com/Art/DUSTEROP/CARDS/ALT_DUSTEROP_P_OR_101/JPG/en_US/507bc8dbcad4c6e0e952712ea55eb43a.jpg",
      "it-it": "",
      "es-es": "",
      "de-de": ""
    },
    "name": "The Reunion",
    "elements": {
      "MAIN_COST": "6",
      "RECALL_COST": "6",
      "MAIN_EFFECT": "{T} : Choose up to the number of cards in your Landmarks:  • Create an [Ordis Recruit 1/1/1] Soldier token in a Companion Expedition.  • Create an [Ordis Recruit 1/1/1] in a Hero Expedition.  • Up to two target Characters gain 1 boost."
    },
    "isSuspended": false,
    "isErrated": false,
    "isBanned": false,
    "isSerialized": false,
    "isParentSerialized": false,
    "collectorNumber": "SDUOP-013-C-EN"
  },
  {
    "@context": "/contexts/Card",
    "@id": "/cards/ALT_DUSTEROP_P_OR_101_R1",
    "@type": "Card",
    "cardType": {
      "@id": "/card_types/01J1Q78N4S1E64PN4T7GB4T59F",
      "@type": "CardType",
      "reference": "LANDMARK_PERMANENT",
      "id": "01J1Q78N4S1E64PN4T7GB4T59F",
      "name": "Landmark Permanent"
    },
    "cardSubTypes": [
      {
        "@type": "CardSubType",
        "@id": "/.well-known/genid/6fe50db4b132ea5318f0",
        "reference": "CONSTRUCTION",
        "id": "01J1SYC159ACKJS202498RAQRR",
        "name": "Construction"
      }
    ],
    "cardSet": {
      "@id": "/card_sets/DUSTEROP",
      "@type": "CardSet",
      "id": "01K4YGEBN10S3MMN6J9CW5B4AC",
      "reference": "DUSTEROP",
      "name": "Seeds of Unity - Organized Play"
    },
    "rarity": {
      "@type": "Rarity",
      "@id": "/.well-known/genid/bbe3d002eb75098c612c",
      "reference": "RARE",
      "id": "01GE7AC9WY6PK56RADXXD6P1T5",
      "name": "Rare"
    },
    "imagePath": "https://altered-prod-eu.s3.amazonaws.com/Art/DUSTEROP/CARDS/ALT_DUSTEROP_P_OR_101/JPG/en_US/b8f31c0fa5ec521cf4532317c6c2950d.jpg",
    "assets": {
      "WEB": [
        "https://altered-prod-eu.s3.amazonaws.com/Art/DUSTEROP/CARDS/ALT_DUSTEROP_P_OR_101/WEB_c5a1c01e8701bc81c04899bbbbf04ba7",
        "https://altered-prod-eu.s3.amazonaws.com/Art/DUSTEROP/CARDS/ALT_DUSTEROP_P_OR_101/WEB_5e52178818bbde434cbbb4977e378013"
      ]
    },
    "lowerPrice": 0,
    "qrUrlDetail": "https://qr.altered.gg/ALT_DUSTEROP_P_OR_101_R1",
    "isOwnerless": false,
    "reference": "ALT_DUSTEROP_P_OR_101_R1",
    "id": "01K4YGECH4RMXXTM87KCSRYQ1R",
    "mainFaction": {
      "@id": "/factions/OR",
      "@type": "Faction",
      "reference": "OR",
      "color": "#0f6593",
      "id": "01GE7AC9X78DXSNKNB15KCF69X",
      "name": "Ordis"
    },
    "allImagePath": {
      "fr-fr": "https://altered-prod-eu.s3.amazonaws.com/Art/DUSTEROP/CARDS/ALT_DUSTEROP_P_OR_101/JPG/fr_FR/415615fb2b10c1503fb668639d790342.jpg",
      "en-us": "https://altered-prod-eu.s3.amazonaws.com/Art/DUSTEROP/CARDS/ALT_DUSTEROP_P_OR_101/JPG/en_US/b8f31c0fa5ec521cf4532317c6c2950d.jpg",
      "it-it": "",
      "es-es": "",
      "de-de": ""
    },
    "name": "The Reunion",
    "elements": {
      "MAIN_COST": "6",
      "RECALL_COST": "6",
      "MAIN_EFFECT": "{T} : Choose up to the number of cards in your Landmarks:  • Create an [Ordis Recruit 1/1/1] Soldier token in a Companion Expedition.  • Create one in a Hero Expedition.  • Up to two target Characters gain 1 boost.  • #Draw a card.#"
    },
    "isSuspended": false,
    "isErrated": false,
    "isBanned": false,
    "isSerialized": false,
    "isParentSerialized": false,
    "collectorNumber": "SDUOP-013-R-EN"
  },
  {
    "@context": "/contexts/Card",
    "@id": "/cards/ALT_DUSTEROP_A_OR_98_C",
    "@type": "Card",
    "cardType": {
      "@id": "/card_types/01GE7AC9X35JXEQZJBBD6E4BKX",
      "@type": "CardType",
      "reference": "SPELL",
      "id": "01GE7AC9X35JXEQZJBBD6E4BKX",
      "name": "Spell"
    },
    "cardSubTypes": [
      {
        "@type": "CardSubType",
        "@id": "/.well-known/genid/90315857e0e759845591",
        "reference": "DISRUPTION",
        "id": "01HKAGPH80FC347E2P8841D298",
        "name": "Disruption"
      },
      {
        "@type": "CardSubType",
        "@id": "/.well-known/genid/452542d350470d43ea0b",
        "reference": "MANEUVER",
        "id": "01HKAGPGT0M24AWMMF30CN0NT4",
        "name": "Maneuver"
      }
    ],
    "cardSet": {
      "@id": "/card_sets/DUSTEROP",
      "@type": "CardSet",
      "id": "01K4YGEBN10S3MMN6J9CW5B4AC",
      "reference": "DUSTEROP",
      "name": "Seeds of Unity - Organized Play"
    },
    "rarity": {
      "@type": "Rarity",
      "@id": "/.well-known/genid/2fcb322542252f542333",
      "reference": "COMMON",
      "id": "01GE7AC9WEQKW1Y1BF8SCY745A",
      "name": "Common"
    },
    "imagePath": "https://altered-prod-eu.s3.amazonaws.com/Art/DUSTEROP/CARDS/ALT_DUSTEROP_A_OR_98/JPG/en_US/640fe4775509172a97a432d3d0675411.jpg",
    "assets": {
      "WEB": [
        "https://altered-prod-eu.s3.amazonaws.com/Art/DUSTEROP/CARDS/ALT_DUSTEROP_A_OR_98/WEB_52cf1121a153eb736f575299ebb7a427",
        "https://altered-prod-eu.s3.amazonaws.com/Art/DUSTEROP/CARDS/ALT_DUSTEROP_A_OR_98/WEB_df1a426454c8edc774fd2d2021175a63"
      ]
    },
    "lowerPrice": 0,
    "qrUrlDetail": "https://qr.altered.gg/ALT_DUSTEROP_A_OR_98_C",
    "isOwnerless": false,
    "reference": "ALT_DUSTEROP_A_OR_98_C",
    "id": "01K4YGECH4RMXXTM87KCSRYQ1Y",
    "mainFaction": {
      "@id": "/factions/OR",
      "@type": "Faction",
      "reference": "OR",
      "color": "#0f6593",
      "id": "01GE7AC9X78DXSNKNB15KCF69X",
      "name": "Ordis"
    },
    "allImagePath": {
      "fr-fr": "https://altered-prod-eu.s3.amazonaws.com/Art/DUSTEROP/CARDS/ALT_DUSTEROP_A_OR_98/JPG/fr_FR/2fcf2659c4ae67869061b95bbe375700.jpg",
      "en-us": "https://altered-prod-eu.s3.amazonaws.com/Art/DUSTEROP/CARDS/ALT_DUSTEROP_A_OR_98/JPG/en_US/640fe4775509172a97a432d3d0675411.jpg",
      "it-it": "",
      "es-es": "",
      "de-de": ""
    },
    "name": "Unfair Encounter",
    "elements": {
      "MAIN_COST": "4",
      "RECALL_COST": "4",
      "MAIN_EFFECT": "[[Fleeting]].  Take control of target Landmark Permanent with Hand Cost {2} or less."
    },
    "isSuspended": false,
    "isErrated": false,
    "isBanned": false,
    "isSerialized": false,
    "isParentSerialized": false,
    "collectorNumber": "SDUOP-018-C-EN"
  },
  {
    "@context": "/contexts/Card",
    "@id": "/cards/ALT_DUSTEROP_A_OR_98_R1",
    "@type": "Card",
    "cardType": {
      "@id": "/card_types/01GE7AC9X35JXEQZJBBD6E4BKX",
      "@type": "CardType",
      "reference": "SPELL",
      "id": "01GE7AC9X35JXEQZJBBD6E4BKX",
      "name": "Spell"
    },
    "cardSubTypes": [
      {
        "@type": "CardSubType",
        "@id": "/.well-known/genid/a0cad9948df5850df382",
        "reference": "DISRUPTION",
        "id": "01HKAGPH80FC347E2P8841D298",
        "name": "Disruption"
      },
      {
        "@type": "CardSubType",
        "@id": "/.well-known/genid/cdce444810efbc0909a5",
        "reference": "MANEUVER",
        "id": "01HKAGPGT0M24AWMMF30CN0NT4",
        "name": "Maneuver"
      }
    ],
    "cardSet": {
      "@id": "/card_sets/DUSTEROP",
      "@type": "CardSet",
      "id": "01K4YGEBN10S3MMN6J9CW5B4AC",
      "reference": "DUSTEROP",
      "name": "Seeds of Unity - Organized Play"
    },
    "rarity": {
      "@type": "Rarity",
      "@id": "/.well-known/genid/b474619d89c828a63718",
      "reference": "RARE",
      "id": "01GE7AC9WY6PK56RADXXD6P1T5",
      "name": "Rare"
    },
    "imagePath": "https://altered-prod-eu.s3.amazonaws.com/Art/DUSTEROP/CARDS/ALT_DUSTEROP_A_OR_98/JPG/en_US/f082eefd282fc2ec2511a756d39550ba.jpg",
    "assets": {
      "WEB": [
        "https://altered-prod-eu.s3.amazonaws.com/Art/DUSTEROP/CARDS/ALT_DUSTEROP_A_OR_98/WEB_52cf1121a153eb736f575299ebb7a427",
        "https://altered-prod-eu.s3.amazonaws.com/Art/DUSTEROP/CARDS/ALT_DUSTEROP_A_OR_98/WEB_df1a426454c8edc774fd2d2021175a63"
      ]
    },
    "lowerPrice": 0,
    "qrUrlDetail": "https://qr.altered.gg/ALT_DUSTEROP_A_OR_98_R1",
    "isOwnerless": false,
    "reference": "ALT_DUSTEROP_A_OR_98_R1",
    "id": "01K4YGECH4RMXXTM87KCSRYQ21",
    "mainFaction": {
      "@id": "/factions/OR",
      "@type": "Faction",
      "reference": "OR",
      "color": "#0f6593",
      "id": "01GE7AC9X78DXSNKNB15KCF69X",
      "name": "Ordis"
    },
    "allImagePath": {
      "fr-fr": "https://altered-prod-eu.s3.amazonaws.com/Art/DUSTEROP/CARDS/ALT_DUSTEROP_A_OR_98/JPG/fr_FR/02098038c920efa24e449d77791e27f5.jpg",
      "en-us": "https://altered-prod-eu.s3.amazonaws.com/Art/DUSTEROP/CARDS/ALT_DUSTEROP_A_OR_98/JPG/en_US/f082eefd282fc2ec2511a756d39550ba.jpg",
      "it-it": "",
      "es-es": "",
      "de-de": ""
    },
    "name": "Unfair Encounter",
    "elements": {
      "MAIN_COST": "#3#",
      "RECALL_COST": "#3#",
      "MAIN_EFFECT": "[[Fleeting]].  Target a Landmark Permanent with Hand Cost {2} or less. #Its controller [Resupplies],# then you take control of it."
    },
    "isSuspended": false,
    "isErrated": false,
    "isBanned": false,
    "isSerialized": false,
    "isParentSerialized": false,
    "collectorNumber": "SDUOP-018-R-EN"
  },
  {
    "@context": "/contexts/Card",
    "@id": "/cards/ALT_DUSTEROP_P_YZ_89_C",
    "@type": "Card",
    "cardType": {
      "@id": "/card_types/01H19NWA92A4ERAC4ATMSZNASS",
      "@type": "CardType",
      "reference": "CHARACTER",
      "id": "01H19NWA92A4ERAC4ATMSZNASS",
      "name": "Character"
    },
    "cardSubTypes": [
      {
        "@type": "CardSubType",
        "@id": "/.well-known/genid/78c185e60a402da5da6c",
        "reference": "ROGUE",
        "id": "01JZ2K0A1NZSGT69DP1WS2917B",
        "name": "Rogue"
      }
    ],
    "cardSet": {
      "@id": "/card_sets/DUSTEROP",
      "@type": "CardSet",
      "id": "01K4YGEBN10S3MMN6J9CW5B4AC",
      "reference": "DUSTEROP",
      "name": "Seeds of Unity - Organized Play"
    },
    "rarity": {
      "@type": "Rarity",
      "@id": "/.well-known/genid/3317f4dd0b6e8cafea71",
      "reference": "COMMON",
      "id": "01GE7AC9WEQKW1Y1BF8SCY745A",
      "name": "Common"
    },
    "imagePath": "https://altered-prod-eu.s3.amazonaws.com/Art/DUSTEROP/CARDS/ALT_DUSTEROP_P_YZ_89/JPG/en_US/7f50b9712041c64fc7f478291a35348b.jpg",
    "assets": {
      "WEB": [
        "https://altered-prod-eu.s3.amazonaws.com/Art/DUSTEROP/CARDS/ALT_DUSTEROP_P_YZ_89/WEB_c71c1f7b3b5aa91839c9df5f6a39eb5e",
        "https://altered-prod-eu.s3.amazonaws.com/Art/DUSTEROP/CARDS/ALT_DUSTEROP_P_YZ_89/WEB_7e74478ddee39e8207cdf99c34ee2602",
        "https://altered-prod-eu.s3.amazonaws.com/Art/DUSTEROP/CARDS/ALT_DUSTEROP_P_YZ_89/WEB_44051affbd93158c2ac866d48b16b6f5"
      ]
    },
    "lowerPrice": 0,
    "qrUrlDetail": "https://qr.altered.gg/ALT_DUSTEROP_P_YZ_89_C",
    "isOwnerless": false,
    "reference": "ALT_DUSTEROP_P_YZ_89_C",
    "id": "01K4YGECH62QHQJ3ED3T58P4SS",
    "mainFaction": {
      "@id": "/factions/YZ",
      "@type": "Faction",
      "reference": "YZ",
      "color": "#764891",
      "id": "01GE7AC9WEQKW1Y1BF8SCY7459",
      "name": "Yzmir"
    },
    "allImagePath": {
      "fr-fr": "https://altered-prod-eu.s3.amazonaws.com/Art/DUSTEROP/CARDS/ALT_DUSTEROP_P_YZ_89/JPG/fr_FR/7563dfa7b6b5baac1672bed0590fc153.jpg",
      "en-us": "https://altered-prod-eu.s3.amazonaws.com/Art/DUSTEROP/CARDS/ALT_DUSTEROP_P_YZ_89/JPG/en_US/7f50b9712041c64fc7f478291a35348b.jpg",
      "it-it": "",
      "es-es": "",
      "de-de": ""
    },
    "name": "Foul Faker",
    "elements": {
      "MAIN_COST": "2",
      "RECALL_COST": "1",
      "OCEAN_POWER": "1",
      "FOREST_POWER": "1",
      "MOUNTAIN_POWER": "1",
      "MAIN_EFFECT": "{H} If I'm [In Contact], [Sabotage]."
    },
    "isSuspended": false,
    "isErrated": false,
    "isBanned": false,
    "isSerialized": false,
    "isParentSerialized": false,
    "collectorNumber": "SDUOP-006-C-EN"
  },
  {
    "@context": "/contexts/Card",
    "@id": "/cards/ALT_DUSTEROP_P_YZ_91_R1",
    "@type": "Card",
    "cardType": {
      "@id": "/card_types/01H19NWA92A4ERAC4ATMSZNASS",
      "@type": "CardType",
      "reference": "CHARACTER",
      "id": "01H19NWA92A4ERAC4ATMSZNASS",
      "name": "Character"
    },
    "cardSubTypes": [
      {
        "@type": "CardSubType",
        "@id": "/.well-known/genid/4b6269043d4576a0e50d",
        "reference": "CITIZEN",
        "id": "01HKAGQWDFDGS8YVZGW98BVV9D",
        "name": "Citizen"
      }
    ],
    "cardSet": {
      "@id": "/card_sets/DUSTEROP",
      "@type": "CardSet",
      "id": "01K4YGEBN10S3MMN6J9CW5B4AC",
      "reference": "DUSTEROP",
      "name": "Seeds of Unity - Organized Play"
    },
    "rarity": {
      "@type": "Rarity",
      "@id": "/.well-known/genid/02cf7994da75f8a914ba",
      "reference": "RARE",
      "id": "01GE7AC9WY6PK56RADXXD6P1T5",
      "name": "Rare"
    },
    "imagePath": "https://altered-prod-eu.s3.amazonaws.com/Art/DUSTEROP/CARDS/ALT_DUSTEROP_P_YZ_91/JPG/en_US/f2afb07238d161ef131526437a842d3d.jpg",
    "assets": {
      "WEB": [
        "https://altered-prod-eu.s3.amazonaws.com/Art/DUSTEROP/CARDS/ALT_DUSTEROP_P_YZ_91/WEB_01ebb49b3e5347270a6595693491934f",
        "https://altered-prod-eu.s3.amazonaws.com/Art/DUSTEROP/CARDS/ALT_DUSTEROP_P_YZ_91/WEB_f233d69c52a6e25b3f56e8ba0c5cb95b",
        "https://altered-prod-eu.s3.amazonaws.com/Art/DUSTEROP/CARDS/ALT_DUSTEROP_P_YZ_91/WEB_5a1914acba589704a70f4c757a17b6c7"
      ]
    },
    "lowerPrice": 0,
    "qrUrlDetail": "https://qr.altered.gg/ALT_DUSTEROP_P_YZ_91_R1",
    "isOwnerless": false,
    "reference": "ALT_DUSTEROP_P_YZ_91_R1",
    "id": "01K4YGECH62QHQJ3ED3T58P4T5",
    "mainFaction": {
      "@id": "/factions/YZ",
      "@type": "Faction",
      "reference": "YZ",
      "color": "#764891",
      "id": "01GE7AC9WEQKW1Y1BF8SCY7459",
      "name": "Yzmir"
    },
    "allImagePath": {
      "fr-fr": "https://altered-prod-eu.s3.amazonaws.com/Art/DUSTEROP/CARDS/ALT_DUSTEROP_P_YZ_91/JPG/fr_FR/ada0947490f80eea9200ae61974f6d82.jpg",
      "en-us": "https://altered-prod-eu.s3.amazonaws.com/Art/DUSTEROP/CARDS/ALT_DUSTEROP_P_YZ_91/JPG/en_US/f2afb07238d161ef131526437a842d3d.jpg",
      "it-it": "",
      "es-es": "",
      "de-de": ""
    },
    "name": "Reka Supporter",
    "elements": {
      "MAIN_COST": "3",
      "RECALL_COST": "2",
      "OCEAN_POWER": "#3#",
      "FOREST_POWER": "2",
      "MOUNTAIN_POWER": "2",
      "MAIN_EFFECT": "{H} Create a [Manaseed] token in your Landmarks.",
      "ECHO_EFFECT": "#{D} : [After You].#"
    },
    "isSuspended": false,
    "isErrated": false,
    "isBanned": false,
    "isSerialized": false,
    "isParentSerialized": false,
    "collectorNumber": "SDUOP-012-R-EN"
  },
  {
    "@context": "/contexts/Card",
    "@id": "/cards/ALT_DUSTEROP_A_AX_98_R2",
    "@type": "Card",
    "cardType": {
      "@id": "/card_types/01GE7AC9X35JXEQZJBBD6E4BKX",
      "@type": "CardType",
      "reference": "SPELL",
      "id": "01GE7AC9X35JXEQZJBBD6E4BKX",
      "name": "Spell"
    },
    "cardSubTypes": [
      {
        "@type": "CardSubType",
        "@id": "/.well-known/genid/e2b65b98d3183f258f56",
        "reference": "CONJURATION",
        "id": "01HKAGQJMGEVS21MCGWDGG8KW0",
        "name": "Conjuration"
      },
      {
        "@type": "CardSubType",
        "@id": "/.well-known/genid/bb9c84c61f03180ff71c",
        "reference": "MANEUVER",
        "id": "01HKAGPGT0M24AWMMF30CN0NT4",
        "name": "Maneuver"
      }
    ],
    "cardSet": {
      "@id": "/card_sets/DUSTEROP",
      "@type": "CardSet",
      "id": "01K4YGEBN10S3MMN6J9CW5B4AC",
      "reference": "DUSTEROP",
      "name": "Seeds of Unity - Organized Play"
    },
    "rarity": {
      "@type": "Rarity",
      "@id": "/.well-known/genid/8e8fcae0173bf38c0f20",
      "reference": "RARE",
      "id": "01GE7AC9WY6PK56RADXXD6P1T5",
      "name": "Rare"
    },
    "imagePath": "https://altered-prod-eu.s3.amazonaws.com/Art/DUSTEROP/CARDS/ALT_DUSTEROP_A_AX_98/JPG/en_US/9bfc1c2ea85175b386c296e653961425.jpg",
    "assets": {
      "WEB": [
        "https://altered-prod-eu.s3.amazonaws.com/Art/DUSTEROP/CARDS/ALT_DUSTEROP_A_AX_98/WEB_3bf03c8d4b745653df54077fc17339e7",
        "https://altered-prod-eu.s3.amazonaws.com/Art/DUSTEROP/CARDS/ALT_DUSTEROP_A_AX_98/WEB_31fa15d61fa8a2f1869d8fce838a0cdd"
      ]
    },
    "lowerPrice": 0,
    "qrUrlDetail": "https://qr.altered.gg/ALT_DUSTEROP_A_AX_98_R2",
    "isOwnerless": false,
    "reference": "ALT_DUSTEROP_A_AX_98_R2",
    "id": "01K4YGECGRVP002XYTEWX1RAK0",
    "mainFaction": {
      "@id": "/factions/YZ",
      "@type": "Faction",
      "reference": "YZ",
      "color": "#764891",
      "id": "01GE7AC9WEQKW1Y1BF8SCY7459",
      "name": "Yzmir"
    },
    "allImagePath": {
      "fr-fr": "https://altered-prod-eu.s3.amazonaws.com/Art/DUSTEROP/CARDS/ALT_DUSTEROP_A_AX_98/JPG/fr_FR/6fd7b8494e51728ef4aec8a5e25d39d3.jpg",
      "en-us": "https://altered-prod-eu.s3.amazonaws.com/Art/DUSTEROP/CARDS/ALT_DUSTEROP_A_AX_98/JPG/en_US/9bfc1c2ea85175b386c296e653961425.jpg",
      "it-it": "",
      "es-es": "",
      "de-de": ""
    },
    "name": "Technological Encounter",
    "elements": {
      "MAIN_COST": "4",
      "RECALL_COST": "2",
      "MAIN_EFFECT": "[Cooldown].  Draw a card, then create a [Manaseed] token in your Landmarks."
    },
    "isSuspended": false,
    "isErrated": false,
    "isBanned": false,
    "isSerialized": false,
    "isParentSerialized": false,
    "collectorNumber": "SDUOP-014-F-EN"
  },
  {
    "@context": "/contexts/Card",
    "@id": "/cards/ALT_DUSTEROP_A_LY_100_R2",
    "@type": "Card",
    "cardType": {
      "@id": "/card_types/01GE7AC9X35JXEQZJBBD6E4BKX",
      "@type": "CardType",
      "reference": "SPELL",
      "id": "01GE7AC9X35JXEQZJBBD6E4BKX",
      "name": "Spell"
    },
    "cardSubTypes": [
      {
        "@type": "CardSubType",
        "@id": "/.well-known/genid/621e4632693c442d88e5",
        "reference": "MANEUVER",
        "id": "01HKAGPGT0M24AWMMF30CN0NT4",
        "name": "Maneuver"
      }
    ],
    "cardSet": {
      "@id": "/card_sets/DUSTEROP",
      "@type": "CardSet",
      "id": "01K4YGEBN10S3MMN6J9CW5B4AC",
      "reference": "DUSTEROP",
      "name": "Seeds of Unity - Organized Play"
    },
    "rarity": {
      "@type": "Rarity",
      "@id": "/.well-known/genid/433b58d94f500c51d65d",
      "reference": "RARE",
      "id": "01GE7AC9WY6PK56RADXXD6P1T5",
      "name": "Rare"
    },
    "imagePath": "https://altered-prod-eu.s3.amazonaws.com/Art/DUSTEROP/CARDS/ALT_DUSTEROP_A_LY_100/JPG/en_US/ce0e69633f83c1efc6e5b9f604120f43.jpg",
    "assets": {
      "WEB": [
        "https://altered-prod-eu.s3.amazonaws.com/Art/DUSTEROP/CARDS/ALT_DUSTEROP_A_LY_100/WEB_bd0ea8beb3bd5e9543a5dcc0d57d3728",
        "https://altered-prod-eu.s3.amazonaws.com/Art/DUSTEROP/CARDS/ALT_DUSTEROP_A_LY_100/WEB_f262966630b2f39074ed083159b59e35"
      ]
    },
    "lowerPrice": 0,
    "qrUrlDetail": "https://qr.altered.gg/ALT_DUSTEROP_A_LY_100_R2",
    "isOwnerless": false,
    "reference": "ALT_DUSTEROP_A_LY_100_R2",
    "id": "01K4YGECGY9XSJBXPCXRG95JZ9",
    "mainFaction": {
      "@id": "/factions/YZ",
      "@type": "Faction",
      "reference": "YZ",
      "color": "#764891",
      "id": "01GE7AC9WEQKW1Y1BF8SCY7459",
      "name": "Yzmir"
    },
    "allImagePath": {
      "fr-fr": "https://altered-prod-eu.s3.amazonaws.com/Art/DUSTEROP/CARDS/ALT_DUSTEROP_A_LY_100/JPG/fr_FR/910ebc417ed7601e8c1aa20edf292755.jpg",
      "en-us": "https://altered-prod-eu.s3.amazonaws.com/Art/DUSTEROP/CARDS/ALT_DUSTEROP_A_LY_100/JPG/en_US/ce0e69633f83c1efc6e5b9f604120f43.jpg",
      "it-it": "",
      "es-es": "",
      "de-de": ""
    },
    "name": "Romantic Encounter",
    "elements": {
      "MAIN_COST": "#7#",
      "RECALL_COST": "#7#",
      "MAIN_EFFECT": "#[[Fleeting]].#  #Do this for each player, starting with you:#  • That player reveals the top four cards of their deck. You may play a Character #with Base Cost {3} or less# from these cards for free and it gains [[Fleeting]], then discard the rest."
    },
    "isSuspended": false,
    "isErrated": false,
    "isBanned": false,
    "isSerialized": false,
    "isParentSerialized": false,
    "collectorNumber": "SDUOP-016-F-EN"
  },
  {
    "@context": "/contexts/Card",
    "@id": "/cards/ALT_DUSTEROP_A_YZ_97_C",
    "@type": "Card",
    "cardType": {
      "@id": "/card_types/01GE7AC9X35JXEQZJBBD6E4BKX",
      "@type": "CardType",
      "reference": "SPELL",
      "id": "01GE7AC9X35JXEQZJBBD6E4BKX",
      "name": "Spell"
    },
    "cardSubTypes": [
      {
        "@type": "CardSubType",
        "@id": "/.well-known/genid/398230f1eb3512d89d3f",
        "reference": "BOON",
        "id": "01HKAGPHVVK20XKBXKCZNGRTFD",
        "name": "Boon"
      },
      {
        "@type": "CardSubType",
        "@id": "/.well-known/genid/a1ed98fa707303f1460c",
        "reference": "MANEUVER",
        "id": "01HKAGPGT0M24AWMMF30CN0NT4",
        "name": "Maneuver"
      }
    ],
    "cardSet": {
      "@id": "/card_sets/DUSTEROP",
      "@type": "CardSet",
      "id": "01K4YGEBN10S3MMN6J9CW5B4AC",
      "reference": "DUSTEROP",
      "name": "Seeds of Unity - Organized Play"
    },
    "rarity": {
      "@type": "Rarity",
      "@id": "/.well-known/genid/39f8eae81cf5958b5280",
      "reference": "COMMON",
      "id": "01GE7AC9WEQKW1Y1BF8SCY745A",
      "name": "Common"
    },
    "imagePath": "https://altered-prod-eu.s3.amazonaws.com/Art/DUSTEROP/CARDS/ALT_DUSTEROP_A_YZ_97/JPG/en_US/1fd4ddedaa44195a1018a58e165beb45.jpg",
    "assets": {
      "WEB": [
        "https://altered-prod-eu.s3.amazonaws.com/Art/DUSTEROP/CARDS/ALT_DUSTEROP_A_YZ_97/WEB_2e7c7af59dda181e0d940fd32adebb2b",
        "https://altered-prod-eu.s3.amazonaws.com/Art/DUSTEROP/CARDS/ALT_DUSTEROP_A_YZ_97/WEB_13dc7089e63dfd3469017779459c3194"
      ]
    },
    "lowerPrice": 0,
    "qrUrlDetail": "https://qr.altered.gg/ALT_DUSTEROP_A_YZ_97_C",
    "isOwnerless": false,
    "reference": "ALT_DUSTEROP_A_YZ_97_C",
    "id": "01K4YGECH75K3EB7FWR6TF39Q6",
    "mainFaction": {
      "@id": "/factions/YZ",
      "@type": "Faction",
      "reference": "YZ",
      "color": "#764891",
      "id": "01GE7AC9WEQKW1Y1BF8SCY7459",
      "name": "Yzmir"
    },
    "allImagePath": {
      "fr-fr": "https://altered-prod-eu.s3.amazonaws.com/Art/DUSTEROP/CARDS/ALT_DUSTEROP_A_YZ_97/JPG/fr_FR/bbcfbe1e39454db909dab437062b5e2e.jpg",
      "en-us": "https://altered-prod-eu.s3.amazonaws.com/Art/DUSTEROP/CARDS/ALT_DUSTEROP_A_YZ_97/JPG/en_US/1fd4ddedaa44195a1018a58e165beb45.jpg",
      "it-it": "",
      "es-es": "",
      "de-de": ""
    },
    "name": "Sports Encounter",
    "elements": {
      "MAIN_COST": "2",
      "RECALL_COST": "4",
      "MAIN_EFFECT": "Distribute 2 boosts among any target Characters in play.",
      "ECHO_EFFECT": "{D}: [After You]."
    },
    "isSuspended": false,
    "isErrated": false,
    "isBanned": false,
    "isSerialized": false,
    "isParentSerialized": false,
    "collectorNumber": "SDUOP-019-C-EN"
  },
  {
    "@context": "/contexts/Card",
    "@id": "/cards/ALT_DUSTEROP_A_YZ_97_R1",
    "@type": "Card",
    "cardType": {
      "@id": "/card_types/01GE7AC9X35JXEQZJBBD6E4BKX",
      "@type": "CardType",
      "reference": "SPELL",
      "id": "01GE7AC9X35JXEQZJBBD6E4BKX",
      "name": "Spell"
    },
    "cardSubTypes": [
      {
        "@type": "CardSubType",
        "@id": "/.well-known/genid/7342a90cef655b4f7430",
        "reference": "BOON",
        "id": "01HKAGPHVVK20XKBXKCZNGRTFD",
        "name": "Boon"
      },
      {
        "@type": "CardSubType",
        "@id": "/.well-known/genid/13bed806e20bbcb5ba4e",
        "reference": "MANEUVER",
        "id": "01HKAGPGT0M24AWMMF30CN0NT4",
        "name": "Maneuver"
      }
    ],
    "cardSet": {
      "@id": "/card_sets/DUSTEROP",
      "@type": "CardSet",
      "id": "01K4YGEBN10S3MMN6J9CW5B4AC",
      "reference": "DUSTEROP",
      "name": "Seeds of Unity - Organized Play"
    },
    "rarity": {
      "@type": "Rarity",
      "@id": "/.well-known/genid/75c2c59f9c7807019dcc",
      "reference": "RARE",
      "id": "01GE7AC9WY6PK56RADXXD6P1T5",
      "name": "Rare"
    },
    "imagePath": "https://altered-prod-eu.s3.amazonaws.com/Art/DUSTEROP/CARDS/ALT_DUSTEROP_A_YZ_97/JPG/en_US/57e4604902e8d3ccbfb7939a864ea085.jpg",
    "assets": {
      "WEB": [
        "https://altered-prod-eu.s3.amazonaws.com/Art/DUSTEROP/CARDS/ALT_DUSTEROP_A_YZ_97/WEB_2e7c7af59dda181e0d940fd32adebb2b",
        "https://altered-prod-eu.s3.amazonaws.com/Art/DUSTEROP/CARDS/ALT_DUSTEROP_A_YZ_97/WEB_13dc7089e63dfd3469017779459c3194"
      ]
    },
    "lowerPrice": 0,
    "qrUrlDetail": "https://qr.altered.gg/ALT_DUSTEROP_A_YZ_97_R1",
    "isOwnerless": false,
    "reference": "ALT_DUSTEROP_A_YZ_97_R1",
    "id": "01K4YGECH75K3EB7FWR6TF39Q9",
    "mainFaction": {
      "@id": "/factions/YZ",
      "@type": "Faction",
      "reference": "YZ",
      "color": "#764891",
      "id": "01GE7AC9WEQKW1Y1BF8SCY7459",
      "name": "Yzmir"
    },
    "allImagePath": {
      "fr-fr": "https://altered-prod-eu.s3.amazonaws.com/Art/DUSTEROP/CARDS/ALT_DUSTEROP_A_YZ_97/JPG/fr_FR/0640451ce3b7de27d8ae75b8ca16f177.jpg",
      "en-us": "https://altered-prod-eu.s3.amazonaws.com/Art/DUSTEROP/CARDS/ALT_DUSTEROP_A_YZ_97/JPG/en_US/57e4604902e8d3ccbfb7939a864ea085.jpg",
      "it-it": "",
      "es-es": "",
      "de-de": ""
    },
    "name": "Sports Encounter",
    "elements": {
      "MAIN_COST": "2",
      "RECALL_COST": "#1#",
      "MAIN_EFFECT": "#[Cooldown].#  Distribute 2 boosts among any target Characters in play #or in Reserve.#",
      "ECHO_EFFECT": "{D}: [After You]."
    },
    "isSuspended": false,
    "isErrated": false,
    "isBanned": false,
    "isSerialized": false,
    "isParentSerialized": false,
    "collectorNumber": "SDUOP-019-R-EN"
  }
]