{"@context":"\/contexts\/CardFilterData","@id":"\/.well-known\/genid\/33cf5d819bdd844ab441","@type":"CardFilterData","factions":[{"@id":"\/factions\/AX","@type":"Faction","reference":"AX","color":"#8c432a","id":"01GE7AC9XBG707G19F03A95TH1","name":"Axiom","description":null},{"@id":"\/factions\/BR","@type":"Faction","reference":"BR","color":"#c32637","id":"01GE7AC9WY6PK56RADXXD6P1T4","name":"Bravos","description":null},{"@id":"\/factions\/LY","@type":"Faction","reference":"LY","color":"#cf4171","id":"01GE7AC9XGB6JE2V63WXWN4FB3","name":"Lyra","description":null},{"@id":"\/factions\/MU","@type":"Faction","reference":"MU","color":"#3d6b42","id":"01GE7AC9X2BNM40TTAYAEFSZSJ","name":"Muna","description":null},{"@id":"\/factions\/OR","@type":"Faction","reference":"OR","color":"#0f6593","id":"01GE7AC9X78DXSNKNB15KCF69X","name":"Ordis","description":null},{"@id":"\/factions\/YZ","@type":"Faction","reference":"YZ","color":"#764891","id":"01GE7AC9WEQKW1Y1BF8SCY7459","name":"Yzmir","description":null}],"cardType":[{"@id":"\/card_types\/01JN9T9WB3A67XPW9251FVSS60","@type":"CardType","reference":"TOKEN_LANDMARK_PERMANENT","id":"01JN9T9WB3A67XPW9251FVSS60","name":"Bleibende Wahrzeichenmarke"},{"@id":"\/card_types\/01J1Q7ASAYXTSM3DH772C70PV5","@type":"CardType","reference":"EXPEDITION_PERMANENT","id":"01J1Q7ASAYXTSM3DH772C70PV5","name":"Bleibende Expeditionskarte"},{"@id":"\/card_types\/01J1Q78N4S1E64PN4T7GB4T59F","@type":"CardType","reference":"LANDMARK_PERMANENT","id":"01J1Q78N4S1E64PN4T7GB4T59F","name":"Bleibende Wahrzeichenkarte"},{"@id":"\/card_types\/01GE7AC9X78DXSNKNB15KCF69Z","@type":"CardType","reference":"PERMANENT","id":"01GE7AC9X78DXSNKNB15KCF69Z","name":"Bleibende Karte"},{"@id":"\/card_types\/01H0FV1VGP26CD3DFE8W3PWTQT","@type":"CardType","reference":"TOKEN","id":"01H0FV1VGP26CD3DFE8W3PWTQT","name":"Marken-Charakter"},{"@id":"\/card_types\/01GE7AC9X35JXEQZJBBD6E4BKX","@type":"CardType","reference":"SPELL","id":"01GE7AC9X35JXEQZJBBD6E4BKX","name":"Zauber"},{"@id":"\/card_types\/01GE7AC9WGQTNRP28T63FH8TZD","@type":"CardType","reference":"HERO","id":"01GE7AC9WGQTNRP28T63FH8TZD","name":"Held"},{"@id":"\/card_types\/01H0FV1VGP4ACD3DFEJW3PWTQT","@type":"CardType","reference":"TOKEN_MANA","id":"01H0FV1VGP4ACD3DFEJW3PWTQT","name":"Mana"},{"@id":"\/card_types\/01H19NWA92A4ERAC4ATMSZNASS","@type":"CardType","reference":"CHARACTER","id":"01H19NWA92A4ERAC4ATMSZNASS","name":"Charakter"}],"cardSet":[{"@id":"\/card_sets\/EOLECB","@type":"CardSet","id":"01KH6E44GRCVN6CHNG9FY4KNXQ","reference":"EOLECB","name":"Roots of Corruption - Collector Booster"},{"@id":"\/card_sets\/EOLE","@type":"CardSet","id":"01K9YWHXF2T6GJJDWAK333TJGV","reference":"EOLE","name":"Roots of Corruption"},{"@id":"\/card_sets\/DUSTER","@type":"CardSet","id":"01K56FXHFTGF3DQ8XE8Q8Y5JG8","reference":"DUSTER","name":"Saat der Eintracht"},{"@id":"\/card_sets\/CYCLONE","@type":"CardSet","id":"01JN9HN8N6WR959TS2XEJWWZ4P","reference":"CYCLONE","name":"Skybound Odyssey"},{"@id":"\/card_sets\/BISE","@type":"CardSet","id":"01JB1YGHBNB4YP1VYJY12XCKJN","reference":"BISE","name":"Whispers from the Maze"},{"@id":"\/card_sets\/ALIZE","@type":"CardSet","id":"01J1Q4NZCDCGMFTFKASM8H29N6","reference":"ALIZE","name":"Trial by Frost"},{"@id":"\/card_sets\/CORE","@type":"CardSet","id":"01HKAFJN3HG3TWKYV0E014K01G","reference":"CORE","name":"Beyond the Gates"},{"@id":"\/card_sets\/COREKS","@type":"CardSet","id":"01HN5TWSSVYM93FHCEC3K8NNCM","reference":"COREKS","name":"Beyond the Gates - KS Edition"}],"cardSetReward":[{"@id":"\/card_sets\/WCS26","@type":"CardSet","id":"01KGWCP9XAFCTT89T9VRTED92Z","reference":"WCS26","name":"World Championship Series 2026"},{"@id":"\/card_sets\/DUSTERCB","@type":"CardSet","id":"01K60PWBQRTWXF3M650SKAQEBE","reference":"DUSTERCB","name":"Seeds of Unity - Collector Booster"},{"@id":"\/card_sets\/DUSTEROP","@type":"CardSet","id":"01K4YGEBN10S3MMN6J9CW5B4AC","reference":"DUSTEROP","name":"Saat der Eintracht - OP"},{"@id":"\/card_sets\/DUSTERTOP","@type":"CardSet","id":"01K571ZHWV0VPWZX736JAJEGAP","reference":"DUSTERTOP","name":"Seeds of Unity - Box Topper"},{"@id":"\/card_sets\/WCF25","@type":"CardSet","id":"01JTJS48D59114PW9E8Z6SQQTN","reference":"WCF25","name":"World Championship 2025 - WORLD CHAMPION CARDS"},{"@id":"\/card_sets\/WCS25","@type":"CardSet","id":"01JTJV0RDYYPKJ3EH4M68H4RKT","reference":"WCS25","name":"World Championship Series 2025"},{"@id":"\/card_sets\/WCQ25","@type":"CardSet","id":"01JTJS33NQTY6A4RPTM11ARJTX","reference":"WCQ25","name":"World Championship Qualifier 2025 - FACTION CHAMPIONS CARDS"},{"@id":"\/card_sets\/JUDGE","@type":"CardSet","id":"01K3TPEHXCWRMR22ZEB5H40XGG","reference":"JUDGE","name":"Judge Rewards"},{"@id":"\/card_sets\/MUSUBI","@type":"CardSet","id":"01K4W8PCZ8QND7585GEK66EFJ9","reference":"MUSUBI","name":"Musubi"},{"@id":"\/card_sets\/TCS3","@type":"CardSet","id":"01JTJS0F8GG1CAXSJ6AEK8495P","reference":"TCS3","name":"Tumult Faction Champion - Set 3"}],"cardSubTypes":[{"@type":"CardSubType","@id":"\/.well-known\/genid\/30a3503d25b0bbde1042","reference":"ADVENTURER","id":"01HKAGPC92CGHANVSRSC8R8ES6","name":"Abenteurer"},{"@type":"CardSubType","@id":"\/.well-known\/genid\/04e3f953f929a9f19380","reference":"ANIMAL","id":"01HKAGQS36Z3DP166MZW8KRAEK","name":"Tier"},{"@type":"CardSubType","@id":"\/.well-known\/genid\/9edd246a832a631051e5","reference":"APPRENTICE","id":"01HKAGPXW29DSBJ0DPFEPFVESC","name":"Lehrling"},{"@type":"CardSubType","@id":"\/.well-known\/genid\/6bf63bc4e3fb4bab7744","reference":"ARTIST","id":"01HKAGQTJ167DYCKKGR8MCESNT","name":"Künstler"},{"@type":"CardSubType","@id":"\/.well-known\/genid\/3131f3348ffc72d70d53","reference":"BOON","id":"01HKAGPHVVK20XKBXKCZNGRTFD","name":"Segen"},{"@type":"CardSubType","@id":"\/.well-known\/genid\/6d76b8d2b1de4164337d","reference":"BUREAUCRAT","id":"01HKAGVBV23NSWD6EXJXSKK3F8","name":"Bürokrat"},{"@type":"CardSubType","@id":"\/.well-known\/genid\/7e56635d742b4e21aa74","reference":"CITIZEN","id":"01HKAGQWDFDGS8YVZGW98BVV9D","name":"Bürger"},{"@type":"CardSubType","@id":"\/.well-known\/genid\/30fbcafcf4361df3dbd3","reference":"COMPANION","id":"01HKAGQPYTEKRYT4PRE9HZHTDA","name":"Gefährte"},{"@type":"CardSubType","@id":"\/.well-known\/genid\/537d662ecedaaf14fa11","reference":"CONJURATION","id":"01HKAGQJMGEVS21MCGWDGG8KW0","name":"Beschwörung"},{"@type":"CardSubType","@id":"\/.well-known\/genid\/5846f260847ae170d2fb","reference":"CONSTRUCTION","id":"01J1SYC159ACKJS202498RAQRR","name":"Konstrukt"},{"@type":"CardSubType","@id":"\/.well-known\/genid\/0c103aa84d631de60eaf","reference":"DEITY","id":"01HKAGPAJFS4YDQVKY6AB16614","name":"Gottheit"},{"@type":"CardSubType","@id":"\/.well-known\/genid\/74d9451c0c2bed39c4c4","reference":"DISRUPTION","id":"01HKAGPH80FC347E2P8841D298","name":"Unterbrechung"},{"@type":"CardSubType","@id":"\/.well-known\/genid\/d96ee995c0eb33b91128","reference":"DRAGON","id":"01HKAGQCSK17FMGRQDPCFZZ4GB","name":"Drache"},{"@type":"CardSubType","@id":"\/.well-known\/genid\/135105410c86470ed3bb","reference":"DRUID","id":"01HKAGS7G3JAKED7MVQKP2G8F7","name":"Druide"},{"@type":"CardSubType","@id":"\/.well-known\/genid\/07bc26e7a31ffbd65885","reference":"ELEMENTAL","id":"01HKAGPA0G5NVDVVXS31BBX2AS","name":"Elementar"},{"@type":"CardSubType","@id":"\/.well-known\/genid\/89ed2a309bff632436e6","reference":"ENGINEER","id":"01HKAGPA9AS71JN0H9HQZTBNCD","name":"Ingenieur"},{"@type":"CardSubType","@id":"\/.well-known\/genid\/9c4fd56537276245329f","reference":"FAIRY","id":"01HKAGPBKC6V2RK28EZGHP8VWW","name":"Fee"},{"@type":"CardSubType","@id":"\/.well-known\/genid\/b61c904edfdc070d8348","reference":"GEAR","id":"01J1QB6WRN6E3REFHBQ6V24VA3","name":"Ausrüstung"},{"@type":"CardSubType","@id":"\/.well-known\/genid\/770fef0b4c6efcd30b3b","reference":"LANDMARK","id":"01HKAGPK6DPRTGYCYJG9XHTRXG","name":"Wahrzeichen"},{"@type":"CardSubType","@id":"\/.well-known\/genid\/2b5243cbef39a8aa6643","reference":"LEVIATHAN","id":"01HKAGQEXKWSBXPSBRBJ2YZ038","name":"Leviathan"},{"@type":"CardSubType","@id":"\/.well-known\/genid\/8f8d6838af54e95dbd39","reference":"MAGE","id":"01HKAGXDF5A4KJW7GVC25YQS3H","name":"Magier"},{"@type":"CardSubType","@id":"\/.well-known\/genid\/517ee6bfcd423bb891ce","reference":"MANEUVER","id":"01HKAGPGT0M24AWMMF30CN0NT4","name":"Manöver"},{"@type":"CardSubType","@id":"\/.well-known\/genid\/e59d076a269240956107","reference":"MERCHANT","id":"01JZ2JZ7RFPB09RFMMFXBG3GZ5","name":"Händler"},{"@type":"CardSubType","@id":"\/.well-known\/genid\/f8d84c3244b8ca80b6c7","reference":"MESSENGER","id":"01HKAGPRRNK7X4TZEBYSPK6DDC","name":"Bote"},{"@type":"CardSubType","@id":"\/.well-known\/genid\/e6ea0357eb76c7ae7d67","reference":"NOBLE","id":"01HKAGVEV163KJH0BWMZ6WR7E9","name":"Adliger"},{"@type":"CardSubType","@id":"\/.well-known\/genid\/9207a983b26da67ca34d","reference":"ORE","id":"01JPYFRDDD06XC6SP7K6W89CTE","name":"Erz"},{"@type":"CardSubType","@id":"\/.well-known\/genid\/220142dbb0449f4c095f","reference":"PLANT","id":"01HKAGSB49H24XWW17AAY441MT","name":"Pflanze"},{"@type":"CardSubType","@id":"\/.well-known\/genid\/ff462530c869c1041309","reference":"ROBOT","id":"01HKAGPDNDJM76PRKTBB98Q0ZM","name":"Roboter"},{"@type":"CardSubType","@id":"\/.well-known\/genid\/ac58f6c1aac9eacd0280","reference":"ROGUE","id":"01JZ2K0A1NZSGT69DP1WS2917B","name":"Rebell"},{"@type":"CardSubType","@id":"\/.well-known\/genid\/cf7eef744a518ae3c4dc","reference":"SCHOLAR","id":"01HKAGRGA2AC23BM29GTJ6XPYE","name":"Gelehrter"},{"@type":"CardSubType","@id":"\/.well-known\/genid\/b4e3ebf7af0c9a4b7860","reference":"SCIENTIST","id":"01JN9V3SNZS1970V4QZF5RDN1Z","name":"Wissenschaftler"},{"@type":"CardSubType","@id":"\/.well-known\/genid\/9946523bc396a3e3b0fe","reference":"SITE","id":"01J1SYC3P1C9H7CT2H8C0WN9CT","name":"Ort"},{"@type":"CardSubType","@id":"\/.well-known\/genid\/4acb4ba19c919df9feec","reference":"SOLDIER","id":"01HKAGQ5CZVEX15T5KTM40KQSA","name":"Soldat"},{"@type":"CardSubType","@id":"\/.well-known\/genid\/27478668f09e557ab3de","reference":"SONG","id":"01HKAGRNJ8WF0FSG4M2MEW7AJ2","name":"Lied"},{"@type":"CardSubType","@id":"\/.well-known\/genid\/dbe6f95c0feceff034f4","reference":"SPIRIT","id":"01HKAGQ2CRATX32S1PS2GBXYV7","name":"Geist"},{"@type":"CardSubType","@id":"\/.well-known\/genid\/2607aa8e0675d5ae4031","reference":"TITAN","id":"01HKAGQ9QZA1N8YNZH7CYPBDVR","name":"Titan"},{"@type":"CardSubType","@id":"\/.well-known\/genid\/4f25c778f3b6cfc46f7d","reference":"TRAINER","id":"01HKAGQ07R8R2DAC69RKNZ5SA6","name":"Trainer"}],"mainCost":["0","1","2","3","4","5","6","7","8","9","10"],"recallCost":["0","1","2","3","4","5","6","7","8","9","10"],"oceanPower":["0","1","2","3","4","5","6","7","8","9","10"],"mountainPower":["0","1","2","3","4","5","6","7","8","9","10"],"forestPower":["0","1","2","3","4","5","6","7","8","9","10"],"rarity":[{"@type":"Rarity","@id":"\/.well-known\/genid\/176b39169833a25a49fc","reference":"COMMON","id":"01GE7AC9WEQKW1Y1BF8SCY745A","name":"Common"},{"@type":"Rarity","@id":"\/.well-known\/genid\/d90dd8093061af5584ca","reference":"RARE","id":"01GE7AC9WY6PK56RADXXD6P1T5","name":"Rare"},{"@type":"Rarity","@id":"\/.well-known\/genid\/cff1ef576b911b30a7e4","reference":"EXALTED","id":"01K3GVRQNY6NY3BCRBY53VDZ58","name":"Exalted"},{"@type":"Rarity","@id":"\/.well-known\/genid\/632c1d57867f45785a57","reference":"UNIQUE","id":"01GE7AC9X35JXEQZJBBD6E4BKW","name":"Unique"}],"keyword":[{"@type":"CardKeyword","@id":"\/.well-known\/genid\/ba6a7e2c888a3920388c","reference":"RESUPPLY","name":"Nachschub"},{"@type":"CardKeyword","@id":"\/.well-known\/genid\/57fa4192512e9b0822b4","reference":"SEASONED","name":"Erfahren"},{"@type":"CardKeyword","@id":"\/.well-known\/genid\/a443148a043bde16cb1f","reference":"BOOSTED","name":"Verstärkt"},{"@type":"CardKeyword","@id":"\/.well-known\/genid\/f62c161f9a39a3b6cbf7","reference":"EXHAUSTED_RESUPPLY","name":"Erschöpfter Nachschub"},{"@type":"CardKeyword","@id":"\/.well-known\/genid\/d71752f06fa2e47a1613","reference":"MANA_MOTH","name":"Mana-Motte 2\/2\/2"},{"@type":"CardKeyword","@id":"\/.well-known\/genid\/81a5b6e610ff81c07e2e","reference":"SCOUT_1","name":"Spähen"},{"@type":"CardKeyword","@id":"\/.well-known\/genid\/3fc6752b9b78d2072372","reference":"SCOUT_2","name":"Spähen"},{"@type":"CardKeyword","@id":"\/.well-known\/genid\/58a874302b5e899f0ee3","reference":"SCOUT_3","name":"Spähen"},{"@type":"CardKeyword","@id":"\/.well-known\/genid\/b4e49f3ff4734d0bc9db","reference":"BRASSBUG","name":"Blechkäfer 2\/2\/2"},{"@type":"CardKeyword","@id":"\/.well-known\/genid\/a498237d6342c07fa85c","reference":"SABOTAGE","name":"Sabotage"},{"@type":"CardKeyword","@id":"\/.well-known\/genid\/a03b3f769071bae5ea1c","reference":"BOODA","name":"Booda 2\/2\/2"},{"@type":"CardKeyword","@id":"\/.well-known\/genid\/ba505028e0b513555f4b","reference":"ORDIS_RECRUIT","name":"Ordis-Rekrut 1\/1\/1"},{"@type":"CardKeyword","@id":"\/.well-known\/genid\/dbc0e2eee2cbfb864ff3","reference":"GIGANTIC","name":"Gigantisch"},{"@type":"CardKeyword","@id":"\/.well-known\/genid\/cc4df0a004944d752993","reference":"TOUGH_1","name":"Robust 1"},{"@type":"CardKeyword","@id":"\/.well-known\/genid\/5694aef03644a8e6958f","reference":"TOUGH_2","name":"Robust 2"},{"@type":"CardKeyword","@id":"\/.well-known\/genid\/5fd519123573709f6a38","reference":"TOUGH_X","name":"Robust X"},{"@type":"CardKeyword","@id":"\/.well-known\/genid\/c208df53768194fdfa81","reference":"DEFENDER","name":"Verteidiger"},{"@type":"CardKeyword","@id":"\/.well-known\/genid\/55136b46cb8d7f16d45a","reference":"ETERNAL","name":"Ewig"},{"@type":"CardKeyword","@id":"\/.well-known\/genid\/b8549d4eeff9d2dc8bfc","reference":"AFTER_YOU","name":"Nach dir"},{"@type":"CardKeyword","@id":"\/.well-known\/genid\/69e04f8ef72fd49bbf6e","reference":"MAW","name":"Schlund 0\/0\/0"},{"@type":"CardKeyword","@id":"\/.well-known\/genid\/ba39ccba89ee4aa314fd","reference":"ANCHORED","name":"Verankert"},{"@type":"CardKeyword","@id":"\/.well-known\/genid\/236246314f934ae120fb","reference":"FLEETING","name":"Vergänglich"},{"@type":"CardKeyword","@id":"\/.well-known\/genid\/fda55afea58e013d4c64","reference":"ASLEEP","name":"Schlafend"},{"@type":"CardKeyword","@id":"\/.well-known\/genid\/30867719ee7943aae723","reference":"SCOUT_4","name":"Spähen"},{"@type":"CardKeyword","@id":"\/.well-known\/genid\/d644c132fa30a38189a3","reference":"COOLDOWN","name":"Abkühlung"},{"@type":"CardKeyword","@id":"\/.well-known\/genid\/acb15fc58677cc6b0443","reference":"DRAGON_SHADE","name":"Drachenecho 5\/5\/5"},{"@type":"CardKeyword","@id":"\/.well-known\/genid\/a5ebba74d9a4c23283c0","reference":"AUGMENT","name":"Erweitern"},{"@type":"CardKeyword","@id":"\/.well-known\/genid\/f2499f897a46692c38dd","reference":"ASCENDS","name":"Aufsteigend"},{"@type":"CardKeyword","@id":"\/.well-known\/genid\/95a8f42312c2b25f38f0","reference":"HALUA","name":"Halua 2\/2\/2"},{"@type":"CardKeyword","@id":"\/.well-known\/genid\/05183e173e046ade7c60","reference":"IN_CONTACT","name":"in Kontakt"},{"@type":"CardKeyword","@id":"\/.well-known\/genid\/d700edc7a3558b936e89","reference":"MANASEED","name":"Manasaaten"},{"@type":"CardKeyword","@id":"\/.well-known\/genid\/48219d3e46f3a97431d7","reference":"GIFT","name":"Geschenk"},{"@type":"CardKeyword","@id":"\/.well-known\/genid\/81eb4b8d973f54283258","reference":"AEROLITH","name":"Aerolit"},{"@type":"CardKeyword","@id":"\/.well-known\/genid\/da80d0b857d4be123249","reference":"RUSH","name":"Forcieren"},{"@type":"CardKeyword","@id":"\/.well-known\/genid\/8c0ab0ada3ec369241a1","reference":"WOOLLYBACK","name":"Wollrücken 1\/1\/1"}],"artist":[{"reference":"Federico Musetti"},{"reference":"Alexandre Honoré"},{"reference":"Sweorkie"},{"reference":"Bastien Jez"},{"reference":"Ina Wong"},{"reference":"Dimas Iswara"},{"reference":"Edward Chee - Seok Yeong"},{"reference":"Max Fiévé"},{"reference":"Zero Wen"},{"reference":"Polar Engine"},{"reference":"Fahmi Fauzi"},{"reference":"Nestor Papatriantafyllou"},{"reference":"Khoa Viet"},{"reference":"HuoMiao Studio"},{"reference":"Damian Audino"},{"reference":"Ba Vo"},{"reference":"Zaeliven"},{"reference":"Romain Kurdi"},{"reference":"Justice Wong"},{"reference":"Edward Cheekokseang"},{"reference":"Gaga Zhou"},{"reference":"Jean-Baptiste Andrier"},{"reference":"Atanas Lozanski"},{"reference":"Kevin Sidharta"},{"reference":"Gael Giudicelli"},{"reference":"Slawek Fedorcuzk"},{"reference":"Lirong Fan"},{"reference":"Zhou jia"},{"reference":"Sebastian Giacobino"},{"reference":"Helder Almeida"},{"reference":"Paris Loannou"},{"reference":"Taras Susak"},{"reference":"Marie Cardouat"},{"reference":"Anh Tung - Ba Vo"},{"reference":"Ed Chee, S.Yong, Stephen"},{"reference":"DOBA"},{"reference":"Rémi Jacquot"},{"reference":"Matteo Spirito"},{"reference":"Fori Y."},{"reference":"Christophe Young"},{"reference":"Exia"},{"reference":"Anh Tung"},{"reference":"Aleksandr Leskinen"},{"reference":"Victor Canton"},{"reference":"Gamon Studio"},{"reference":"Iris Wincker"},{"reference":"Aaron Ming"},{"reference":"Tristan Bideau"},{"reference":"Leena Sooba"},{"reference":"Denice Vis"},{"reference":"Andy Jauffrit"},{"reference":"Jefrey Yonathan"},{"reference":"Julien Carrasco"},{"reference":"Martin Mottet"},{"reference":"Saeed Jalabi"},{"reference":"Jamin Amaral Fernandez"},{"reference":"Abigael Giroud"},{"reference":"Seppyo"}],"cardProducts":[{"@id":"\/card_products\/01HTNF0R63ZVZDCJXX0SQ8G55F","@type":"CardProduct","reference":"A","name":"AltArt"},{"@id":"\/card_products\/01H1NW5YEN8B72T6CXPYDXV5CZ","@type":"CardProduct","reference":"B","name":"Booster"},{"@id":"\/card_products\/01HNWTR4M752KF9JK6J4SH2R6M","@type":"CardProduct","reference":"P","name":"Promotion"}]}