{
  "@context": "/contexts/Card",
  "@id": "/cards",
  "@type": "hydra:Collection",
  "hydra:totalItems": 6,
  "hydra:member": [
    {
      "id": "01K4YGECGXZMF34SHDVQ6H347Z",
      "cardType": {
        "@id": "/card_types/01H19NWA92A4ERAC4ATMSZNASS",
        "@type": "CardType",
        "reference": "CHARACTER",
        "id": "01H19NWA92A4ERAC4ATMSZNASS",
        "name": "Character"
      },
      "cardSet": {
        "@id": "/card_sets/DUSTEROP",
        "@type": "CardSet",
        "id": "01K4YGEBN10S3MMN6J9CW5B4AC",
        "reference": "DUSTEROP",
        "name": "Seeds of Unity - Organized Play"
      },
      "cardSubTypes": [],
      "rarity": {
        "@type": "Rarity",
        "@id": "/.well-known/genid/f68dfd8560f08e290d64",
        "reference": "COMMON",
        "id": "01GE7AC9WEQKW1Y1BF8SCY745A",
        "name": "Common"
      },
      "imagePath": "https://altered-prod-eu.s3.amazonaws.com/Art/DUSTEROP/CARDS/ALT_DUSTEROP_P_LY_87/JPG/en_US/026ea040b5f9d76eddd18f5b97ea46e4.jpg",
      "assets": {
        "WEB": [
          "https://altered-prod-eu.s3.amazonaws.com/Art/DUSTEROP/CARDS/ALT_DUSTEROP_P_LY_87/WEB_3def63fd4f71e19155c9ab1778b1a453",
          "https://altered-prod-eu.s3.amazonaws.com/Art/DUSTEROP/CARDS/ALT_DUSTEROP_P_LY_87/WEB_46cdc5a82582519a48465523f7e3ec81",
          "https://altered-prod-eu.s3.amazonaws.com/Art/DUSTEROP/CARDS/ALT_DUSTEROP_P_LY_87/WEB_ab973cc46a201c7dead41627e82d59fb"
        ]
      },
      "qrUrlDetail": "https://qr.altered.gg/ALT_DUSTEROP_P_LY_87_C",
      "mainFaction": {
        "@id": "/factions/LY",
        "@type": "Faction",
        "reference": "LY",
        "color": "#cf4171",
        "id": "01GE7AC9XGB6JE2V63WXWN4FB3",
        "name": "Lyra"
      },
      "name": "Reka Guide",
      "elements": {
        "MAIN_COST": "2",
        "RECALL_COST": "2",
        "MOUNTAIN_POWER": "2",
        "OCEAN_POWER": "1",
        "FOREST_POWER": "2"
      },
      "isOwnerless": false,
      "cardFamilyReference": "LY_87",
      "allImagePath": {
        "fr-fr": "https://altered-prod-eu.s3.amazonaws.com/Art/DUSTEROP/CARDS/ALT_DUSTEROP_P_LY_87/JPG/fr_FR/2d57ad72fb1f6f2347963422a5d3286b.jpg",
        "en-us": "https://altered-prod-eu.s3.amazonaws.com/Art/DUSTEROP/CARDS/ALT_DUSTEROP_P_LY_87/JPG/en_US/026ea040b5f9d76eddd18f5b97ea46e4.jpg",
        "it-it": "https://altered-prod-eu.s3.amazonaws.com/Art/DUSTEROP/CARDS/ALT_DUSTEROP_P_LY_87/JPG/it_IT/f07b9f96afd74f0621c352a1c7c8b4ff.jpg",
        "es-es": "https://altered-prod-eu.s3.amazonaws.com/Art/DUSTEROP/CARDS/ALT_DUSTEROP_P_LY_87/JPG/es_ES/776d00e1d80c6483dcc533a9cee0631d.jpg",
        "de-de": "https://altered-prod-eu.s3.amazonaws.com/Art/DUSTEROP/CARDS/ALT_DUSTEROP_P_LY_87/JPG/de_DE/91c145b59076f302ff4a681e101b6f46.jpg"
      },
      "cardHistoryStatus": null,
      "isSuspended": false,
      "isErrated": false,
      "isBanned": false,
      "reference": "ALT_DUSTEROP_P_LY_87_C",
      "isSerialized": false,
      "isParentSerialized": false,
      "@id": "/cards/ALT_DUSTEROP_P_LY_87_C"
    },
    {
      "id": "01K4YGECGY9XSJBXPCXRG95JYX",
      "cardType": {
        "@id": "/card_types/01H19NWA92A4ERAC4ATMSZNASS",
        "@type": "CardType",
        "reference": "CHARACTER",
        "id": "01H19NWA92A4ERAC4ATMSZNASS",
        "name": "Character"
      },
      "cardSet": {
        "@id": "/card_sets/DUSTEROP",
        "@type": "CardSet",
        "id": "01K4YGEBN10S3MMN6J9CW5B4AC",
        "reference": "DUSTEROP",
        "name": "Seeds of Unity - Organized Play"
      },
      "cardSubTypes": [],
      "rarity": {
        "@type": "Rarity",
        "@id": "/.well-known/genid/c918f34c08102c023025",
        "reference": "RARE",
        "id": "01GE7AC9WY6PK56RADXXD6P1T5",
        "name": "Rare"
      },
      "imagePath": "https://altered-prod-eu.s3.amazonaws.com/Art/DUSTEROP/CARDS/ALT_DUSTEROP_P_LY_94/JPG/en_US/f41a1908268212c5035e4210a5e94765.jpg",
      "assets": {
        "WEB": [
          "https://altered-prod-eu.s3.amazonaws.com/Art/DUSTEROP/CARDS/ALT_DUSTEROP_P_LY_94/WEB_92687b5e03b4f6de17bdb43e1ad773d3",
          "https://altered-prod-eu.s3.amazonaws.com/Art/DUSTEROP/CARDS/ALT_DUSTEROP_P_LY_94/WEB_73ea2a25d9b8dd7da78a09ab7277437c",
          "https://altered-prod-eu.s3.amazonaws.com/Art/DUSTEROP/CARDS/ALT_DUSTEROP_P_LY_94/WEB_905f146916579072324a60c42eb9991d"
        ]
      },
      "qrUrlDetail": "https://qr.altered.gg/ALT_DUSTEROP_P_LY_94_R1",
      "mainFaction": {
        "@id": "/factions/LY",
        "@type": "Faction",
        "reference": "LY",
        "color": "#cf4171",
        "id": "01GE7AC9XGB6JE2V63WXWN4FB3",
        "name": "Lyra"
      },
      "name": "Nightclub Bouncer",
      "elements": {
        "MAIN_COST": "3",
        "RECALL_COST": "3",
        "MOUNTAIN_POWER": "0",
        "OCEAN_POWER": "4",
        "FOREST_POWER": "4"
      },
      "isOwnerless": false,
      "cardFamilyReference": "LY_94",
      "allImagePath": {
        "fr-fr": "https://altered-prod-eu.s3.amazonaws.com/Art/DUSTEROP/CARDS/ALT_DUSTEROP_P_LY_94/JPG/fr_FR/ec3b1a8456c0ae2f58a89b259844ce77.jpg",
        "en-us": "https://altered-prod-eu.s3.amazonaws.com/Art/DUSTEROP/CARDS/ALT_DUSTEROP_P_LY_94/JPG/en_US/f41a1908268212c5035e4210a5e94765.jpg",
        "it-it": "https://altered-prod-eu.s3.amazonaws.com/Art/DUSTEROP/CARDS/ALT_DUSTEROP_P_LY_94/JPG/it_IT/fe2883c6b9f53c59cacf5e3d6493fa72.jpg",
        "es-es": "https://altered-prod-eu.s3.amazonaws.com/Art/DUSTEROP/CARDS/ALT_DUSTEROP_P_LY_94/JPG/es_ES/36620a31f1cc7bdbab54daf4641e7156.jpg",
        "de-de": "https://altered-prod-eu.s3.amazonaws.com/Art/DUSTEROP/CARDS/ALT_DUSTEROP_P_LY_94/JPG/de_DE/4f8bf10d0d3e7d329e226cce7efaa124.jpg"
      },
      "cardHistoryStatus": null,
      "isSuspended": false,
      "isErrated": false,
      "isBanned": false,
      "reference": "ALT_DUSTEROP_P_LY_94_R1",
      "isSerialized": false,
      "isParentSerialized": false,
      "@id": "/cards/ALT_DUSTEROP_P_LY_94_R1"
    },
    {
      "id": "01K4YGECGY9XSJBXPCXRG95JZ3",
      "cardType": {
        "@id": "/card_types/01GE7AC9X35JXEQZJBBD6E4BKX",
        "@type": "CardType",
        "reference": "SPELL",
        "id": "01GE7AC9X35JXEQZJBBD6E4BKX",
        "name": "Spell"
      },
      "cardSet": {
        "@id": "/card_sets/DUSTEROP",
        "@type": "CardSet",
        "id": "01K4YGEBN10S3MMN6J9CW5B4AC",
        "reference": "DUSTEROP",
        "name": "Seeds of Unity - Organized Play"
      },
      "cardSubTypes": [],
      "rarity": {
        "@type": "Rarity",
        "@id": "/.well-known/genid/f68dfd8560f08e290d64",
        "reference": "COMMON",
        "id": "01GE7AC9WEQKW1Y1BF8SCY745A",
        "name": "Common"
      },
      "imagePath": "https://altered-prod-eu.s3.amazonaws.com/Art/DUSTEROP/CARDS/ALT_DUSTEROP_A_LY_100/JPG/en_US/559bb7dd9c965e1c3f2d195d97cd9c7a.jpg",
      "assets": {
        "WEB": [
          "https://altered-prod-eu.s3.amazonaws.com/Art/DUSTEROP/CARDS/ALT_DUSTEROP_A_LY_100/WEB_bd0ea8beb3bd5e9543a5dcc0d57d3728",
          "https://altered-prod-eu.s3.amazonaws.com/Art/DUSTEROP/CARDS/ALT_DUSTEROP_A_LY_100/WEB_f262966630b2f39074ed083159b59e35"
        ]
      },
      "qrUrlDetail": "https://qr.altered.gg/ALT_DUSTEROP_A_LY_100_C",
      "mainFaction": {
        "@id": "/factions/LY",
        "@type": "Faction",
        "reference": "LY",
        "color": "#cf4171",
        "id": "01GE7AC9XGB6JE2V63WXWN4FB3",
        "name": "Lyra"
      },
      "name": "Romantic Encounter",
      "elements": {
        "MAIN_COST": "4",
        "RECALL_COST": "4",
        "MOUNTAIN_POWER": "0",
        "OCEAN_POWER": "0",
        "FOREST_POWER": "0"
      },
      "isOwnerless": false,
      "cardFamilyReference": "LY_100",
      "allImagePath": {
        "fr-fr": "https://altered-prod-eu.s3.amazonaws.com/Art/DUSTEROP/CARDS/ALT_DUSTEROP_A_LY_100/JPG/fr_FR/2e52df9b7343c0f47e9306a497fbe597.jpg",
        "en-us": "https://altered-prod-eu.s3.amazonaws.com/Art/DUSTEROP/CARDS/ALT_DUSTEROP_A_LY_100/JPG/en_US/559bb7dd9c965e1c3f2d195d97cd9c7a.jpg",
        "it-it": "https://altered-prod-eu.s3.amazonaws.com/Art/DUSTEROP/CARDS/ALT_DUSTEROP_A_LY_100/JPG/it_IT/1f9a60032f78daba6ccfb02b2e11e1cf.jpg",
        "es-es": "https://altered-prod-eu.s3.amazonaws.com/Art/DUSTEROP/CARDS/ALT_DUSTEROP_A_LY_100/JPG/es_ES/a1f59ba61fec48ed1d2b4010177ac2ce.jpg",
        "de-de": "https://altered-prod-eu.s3.amazonaws.com/Art/DUSTEROP/CARDS/ALT_DUSTEROP_A_LY_100/JPG/de_DE/e33214c3e9ccf9619401c8cb3b8f8527.jpg"
      },
      "cardHistoryStatus": null,
      "isSuspended": false,
      "isErrated": false,
      "isBanned": false,
      "reference": "ALT_DUSTEROP_A_LY_100_C",
      "isSerialized": false,
      "isParentSerialized": false,
      "@id": "/cards/ALT_DUSTEROP_A_LY_100_C"
    },
    {
      "id": "01K4YGECGY9XSJBXPCXRG95JZ6",
      "cardType": {
        "@id": "/card_types/01GE7AC9X35JXEQZJBBD6E4BKX",
        "@type": "CardType",
        "reference": "SPELL",
        "id": "01GE7AC9X35JXEQZJBBD6E4BKX",
        "name": "Spell"
      },
      "cardSet": {
        "@id": "/card_sets/DUSTEROP",
        "@type": "CardSet",
        "id": "01K4YGEBN10S3MMN6J9CW5B4AC",
        "reference": "DUSTEROP",
        "name": "Seeds of Unity - Organized Play"
      },
      "cardSubTypes": [],
      "rarity": {
        "@type": "Rarity",
        "@id": "/.well-known/genid/c918f34c08102c023025",
        "reference": "RARE",
        "id": "01GE7AC9WY6PK56RADXXD6P1T5",
        "name": "Rare"
      },
      "imagePath": "https://altered-prod-eu.s3.amazonaws.com/Art/DUSTEROP/CARDS/ALT_DUSTEROP_A_LY_100/JPG/en_US/b213df7024efc3cf8ab5b9e7dd08fbdb.jpg",
      "assets": {
        "WEB": [
          "https://altered-prod-eu.s3.amazonaws.com/Art/DUSTEROP/CARDS/ALT_DUSTEROP_A_LY_100/WEB_bd0ea8beb3bd5e9543a5dcc0d57d3728",
          "https://altered-prod-eu.s3.amazonaws.com/Art/DUSTEROP/CARDS/ALT_DUSTEROP_A_LY_100/WEB_f262966630b2f39074ed083159b59e35"
        ]
      },
      "qrUrlDetail": "https://qr.altered.gg/ALT_DUSTEROP_A_LY_100_R1",
      "mainFaction": {
        "@id": "/factions/LY",
        "@type": "Faction",
        "reference": "LY",
        "color": "#cf4171",
        "id": "01GE7AC9XGB6JE2V63WXWN4FB3",
        "name": "Lyra"
      },
      "name": "Romantic Encounter",
      "elements": {
        "MAIN_COST": "7",
        "RECALL_COST": "7",
        "MOUNTAIN_POWER": "0",
        "OCEAN_POWER": "0",
        "FOREST_POWER": "0"
      },
      "isOwnerless": false,
      "cardFamilyReference": "LY_100",
      "allImagePath": {
        "fr-fr": "https://altered-prod-eu.s3.amazonaws.com/Art/DUSTEROP/CARDS/ALT_DUSTEROP_A_LY_100/JPG/fr_FR/0f30b3967460129a7bf4a8676201f25f.jpg",
        "en-us": "https://altered-prod-eu.s3.amazonaws.com/Art/DUSTEROP/CARDS/ALT_DUSTEROP_A_LY_100/JPG/en_US/b213df7024efc3cf8ab5b9e7dd08fbdb.jpg",
        "it-it": "https://altered-prod-eu.s3.amazonaws.com/Art/DUSTEROP/CARDS/ALT_DUSTEROP_A_LY_100/JPG/it_IT/7576a91c4c84434f9971c950cab49523.jpg",
        "es-es": "https://altered-prod-eu.s3.amazonaws.com/Art/DUSTEROP/CARDS/ALT_DUSTEROP_A_LY_100/JPG/es_ES/555553124e6d0b119e973f1696624943.jpg",
        "de-de": "https://altered-prod-eu.s3.amazonaws.com/Art/DUSTEROP/CARDS/ALT_DUSTEROP_A_LY_100/JPG/de_DE/bae7d2b5a58d20346feba6cd967c1e27.jpg"
      },
      "cardHistoryStatus": null,
      "isSuspended": false,
      "isErrated": false,
      "isBanned": false,
      "reference": "ALT_DUSTEROP_A_LY_100_R1",
      "isSerialized": false,
      "isParentSerialized": false,
      "@id": "/cards/ALT_DUSTEROP_A_LY_100_R1"
    },
    {
      "id": "01K4YGECH13XFX6RFD000JVSWD",
      "cardType": {
        "@id": "/card_types/01GE7AC9X35JXEQZJBBD6E4BKX",
        "@type": "CardType",
        "reference": "SPELL",
        "id": "01GE7AC9X35JXEQZJBBD6E4BKX",
        "name": "Spell"
      },
      "cardSet": {
        "@id": "/card_sets/DUSTEROP",
        "@type": "CardSet",
        "id": "01K4YGEBN10S3MMN6J9CW5B4AC",
        "reference": "DUSTEROP",
        "name": "Seeds of Unity - Organized Play"
      },
      "cardSubTypes": [],
      "rarity": {
        "@type": "Rarity",
        "@id": "/.well-known/genid/c918f34c08102c023025",
        "reference": "RARE",
        "id": "01GE7AC9WY6PK56RADXXD6P1T5",
        "name": "Rare"
      },
      "imagePath": "https://altered-prod-eu.s3.amazonaws.com/Art/DUSTEROP/CARDS/ALT_DUSTEROP_A_MU_98/JPG/en_US/43ac5fe2e15c658ed55ac7307f24080d.jpg",
      "assets": {
        "WEB": [
          "https://altered-prod-eu.s3.amazonaws.com/Art/DUSTEROP/CARDS/ALT_DUSTEROP_A_MU_98/WEB_88deb0b8dbb774637986dfd99042de98",
          "https://altered-prod-eu.s3.amazonaws.com/Art/DUSTEROP/CARDS/ALT_DUSTEROP_A_MU_98/WEB_eeacf8ec4015ecda3528b920398f8506"
        ]
      },
      "qrUrlDetail": "https://qr.altered.gg/ALT_DUSTEROP_A_MU_98_R2",
      "mainFaction": {
        "@id": "/factions/LY",
        "@type": "Faction",
        "reference": "LY",
        "color": "#cf4171",
        "id": "01GE7AC9XGB6JE2V63WXWN4FB3",
        "name": "Lyra"
      },
      "name": "Soul Encounter",
      "elements": {
        "MAIN_COST": "3",
        "RECALL_COST": "2",
        "MOUNTAIN_POWER": "0",
        "OCEAN_POWER": "0",
        "FOREST_POWER": "0"
      },
      "isOwnerless": false,
      "cardFamilyReference": "MU_98",
      "allImagePath": {
        "fr-fr": "https://altered-prod-eu.s3.amazonaws.com/Art/DUSTEROP/CARDS/ALT_DUSTEROP_A_MU_98/JPG/fr_FR/36657fbd43767be370ce31f006ff5ec3.jpg",
        "en-us": "https://altered-prod-eu.s3.amazonaws.com/Art/DUSTEROP/CARDS/ALT_DUSTEROP_A_MU_98/JPG/en_US/43ac5fe2e15c658ed55ac7307f24080d.jpg",
        "it-it": "https://altered-prod-eu.s3.amazonaws.com/Art/DUSTEROP/CARDS/ALT_DUSTEROP_A_MU_98/JPG/it_IT/fcd03b474f0de9084ef6dbb0335750ef.jpg",
        "es-es": "https://altered-prod-eu.s3.amazonaws.com/Art/DUSTEROP/CARDS/ALT_DUSTEROP_A_MU_98/JPG/es_ES/d34757b8c8e2a056ba5542946bcc646a.jpg",
        "de-de": "https://altered-prod-eu.s3.amazonaws.com/Art/DUSTEROP/CARDS/ALT_DUSTEROP_A_MU_98/JPG/de_DE/b90e937adc952f9b5500b15fdc50aefb.jpg"
      },
      "cardHistoryStatus": null,
      "isSuspended": false,
      "isErrated": false,
      "isBanned": false,
      "reference": "ALT_DUSTEROP_A_MU_98_R2",
      "isSerialized": false,
      "isParentSerialized": false,
      "@id": "/cards/ALT_DUSTEROP_A_MU_98_R2"
    },
    {
      "id": "01K4YGECH5B52PVNSD8WASC8VP",
      "cardType": {
        "@id": "/card_types/01GE7AC9X35JXEQZJBBD6E4BKX",
        "@type": "CardType",
        "reference": "SPELL",
        "id": "01GE7AC9X35JXEQZJBBD6E4BKX",
        "name": "Spell"
      },
      "cardSet": {
        "@id": "/card_sets/DUSTEROP",
        "@type": "CardSet",
        "id": "01K4YGEBN10S3MMN6J9CW5B4AC",
        "reference": "DUSTEROP",
        "name": "Seeds of Unity - Organized Play"
      },
      "cardSubTypes": [],
      "rarity": {
        "@type": "Rarity",
        "@id": "/.well-known/genid/c918f34c08102c023025",
        "reference": "RARE",
        "id": "01GE7AC9WY6PK56RADXXD6P1T5",
        "name": "Rare"
      },
      "imagePath": "https://altered-prod-eu.s3.amazonaws.com/Art/DUSTEROP/CARDS/ALT_DUSTEROP_A_OR_98/JPG/en_US/637c61241d270f8f0a755e8c6ba3ac94.jpg",
      "assets": {
        "WEB": [
          "https://altered-prod-eu.s3.amazonaws.com/Art/DUSTEROP/CARDS/ALT_DUSTEROP_A_OR_98/WEB_52cf1121a153eb736f575299ebb7a427",
          "https://altered-prod-eu.s3.amazonaws.com/Art/DUSTEROP/CARDS/ALT_DUSTEROP_A_OR_98/WEB_df1a426454c8edc774fd2d2021175a63"
        ]
      },
      "qrUrlDetail": "https://qr.altered.gg/ALT_DUSTEROP_A_OR_98_R2",
      "mainFaction": {
        "@id": "/factions/LY",
        "@type": "Faction",
        "reference": "LY",
        "color": "#cf4171",
        "id": "01GE7AC9XGB6JE2V63WXWN4FB3",
        "name": "Lyra"
      },
      "name": "Unfair Encounter",
      "elements": {
        "MAIN_COST": "3",
        "RECALL_COST": "3",
        "MOUNTAIN_POWER": "0",
        "OCEAN_POWER": "0",
        "FOREST_POWER": "0"
      },
      "isOwnerless": false,
      "cardFamilyReference": "OR_98",
      "allImagePath": {
        "fr-fr": "https://altered-prod-eu.s3.amazonaws.com/Art/DUSTEROP/CARDS/ALT_DUSTEROP_A_OR_98/JPG/fr_FR/75e40cd79bd672beee196f083b683ea8.jpg",
        "en-us": "https://altered-prod-eu.s3.amazonaws.com/Art/DUSTEROP/CARDS/ALT_DUSTEROP_A_OR_98/JPG/en_US/637c61241d270f8f0a755e8c6ba3ac94.jpg",
        "it-it": "https://altered-prod-eu.s3.amazonaws.com/Art/DUSTEROP/CARDS/ALT_DUSTEROP_A_OR_98/JPG/it_IT/9b36deb7f75cab1669e03f320b2c4d71.jpg",
        "es-es": "https://altered-prod-eu.s3.amazonaws.com/Art/DUSTEROP/CARDS/ALT_DUSTEROP_A_OR_98/JPG/es_ES/6c5a4a8ca32815a7f42e7157f1ffd3e8.jpg",
        "de-de": "https://altered-prod-eu.s3.amazonaws.com/Art/DUSTEROP/CARDS/ALT_DUSTEROP_A_OR_98/JPG/de_DE/82b74938f4c480c6ec9d57263db463ec.jpg"
      },
      "cardHistoryStatus": null,
      "isSuspended": false,
      "isErrated": false,
      "isBanned": false,
      "reference": "ALT_DUSTEROP_A_OR_98_R2",
      "isSerialized": false,
      "isParentSerialized": false,
      "@id": "/cards/ALT_DUSTEROP_A_OR_98_R2"
    }
  ]
}